fsm.v
`define ADDRESS 3'd00
`define MISO_REG 3'd1
`define MISO_OUT 3'd2
`define MOSI_MEM 3'd3
`define MOSI_WRI 3'd4
`define PreADDRESS 3'd6
`define OFF 3'd5
module fsm
(
  input cs,
  input sclk,
  input  shiftRegOut0,
  output add_WE,
  output DM_WE,
  output SR_WE,
  output MISO_Buff, 
  output[4:0] counter
  );
      reg[2:0] state;

      initial state = `OFF;

      reg[4:0] counter;

      reg add_WE, DM_WE, SR_WE, MISO_Buff;

      always @(posedge sclk) begin


      //case (state)
       // `ADDRESS:   begin add_WE <= 1; DM_WE<=0; SR_WE <= 0; MISO_Buff <= 0; end
      // `MISO_REG:  begin add_WE <= 0; DM_WE<=0; SR_WE <= 1; MISO_Buff <= 0; end
      //   `MOSI_MEM:  begin add_WE <= 0; DM_WE<=0; SR_WE <= 0; MISO_Buff <= 0; end
      //   `MISO_OUT:  begin add_WE <= 0; DM_WE<=0; SR_WE <= 0; MISO_Buff <= 1; end
      //   `MOSI_WRI:  begin add_WE <= 0; DM_WE<=1; SR_WE <= 0; MISO_Buff <= 0; end
      //   `OFF:       begin add_WE <= 0; DM_WE<=0; SR_WE <= 0; MISO_Buff <= 0; end
      // endcase


      $display("Counter %d, State %d, add %b, dm %b, sr %b, buff %b, cs %b, shiftRegOut0, %b", counter, state, add_WE, DM_WE, SR_WE, MISO_Buff, cs, shiftRegOut0);
      counter <= counter+1;

      if (cs) begin
        state <= `OFF;
        counter <= 0;
      end

      else if (cs == 0 && state == `OFF) begin
        counter <= counter+1;
        if (counter == 6) begin  // Wait for 7 bits to clock in. Takes an extra clock for everything to push through the FSM
          state <= `PreADDRESS;
        end
      end
      else if (state == `PreADDRESS)begin
        state <= `ADDRESS;
      end
      else if (state == `ADDRESS && shiftRegOut0 == 1) begin
        state <= `MISO_REG;
      end

      else if (state == `MISO_REG)begin
        state <= `MISO_OUT;
        counter <= 0;
      end

      else if (state == `MISO_OUT)begin
        if (counter == 7 + 1) begin  // Wait for 8 bits to clock out. Takes an extra clock for everything to push through the FSM
          state <= `OFF;
          end
      end

      else if (state == `ADDRESS && shiftRegOut0 == 0) begin
        state <= `MOSI_MEM;
        counter <= 0;
      end

      else if(state == `MOSI_MEM) begin
        if (counter == 6) begin // Wait for 8 bits to clock in (immediately on the 8th, change memory). Takes an extra clock for everything to push through the FSM
          state <= `MOSI_WRI;
          end
      end

      else if (state == `MOSI_WRI)begin
        state <= `OFF;
      end

  end


    always @ (state) begin
          case (state)
        `PreADDRESS: begin add_WE <=1; DM_WE<=0; SR_WE <= 0; MISO_Buff <= 0; end
        `ADDRESS:   begin add_WE <= 0; DM_WE<=0; SR_WE <= 0; MISO_Buff <= 0; end
        `MISO_REG:  begin add_WE <= 0; DM_WE<=0; SR_WE <= 1; MISO_Buff <= 0; end
        `MOSI_MEM:  begin add_WE <= 0; DM_WE<=0; SR_WE <= 0; MISO_Buff <= 0; end
        `MISO_OUT:  begin add_WE <= 0; DM_WE<=0; SR_WE <= 0; MISO_Buff <= 1; end
        `MOSI_WRI:  begin add_WE <= 0; DM_WE<=1; SR_WE <= 0; MISO_Buff <= 0; end
        `OFF:       begin add_WE <= 0; DM_WE<=0; SR_WE <= 0; MISO_Buff <= 0; end
      endcase
      end


  endmodule

fsm.t.v
`include "fsm.v"

module testfsm();

  reg cs;
  reg sclk;
  reg  shiftRegOut0;
  wire add_WE;
  wire DM_WE;
  wire SR_WE;
  wire MISO_Buff;
  wire [4:0] counter;

  initial shiftRegOut0 = 1;
  initial cs = 1;
  initial sclk = 1;


  fsm fsm1(.cs(cs),
            .sclk(sclk),
            .counter(counter),
            .shiftRegOut0(shiftRegOut0),
            .add_WE(add_WE),
            .DM_WE(DM_WE),
            .SR_WE(SR_WE),
            .MISO_Buff(MISO_Buff));
    

    initial begin

    $dumpfile("fsm.vcd");
    $dumpvars();
  

    sclk <= 0; # 10
    sclk <= 1; # 10

    //  WRITE OP TSTING
    $display("Write op testing");

    shiftRegOut0 <= 0; 

    sclk <= 0; 
    cs <= 0; # 10
    sclk = 1; # 10

    

    sclk <= 0; # 10
    sclk <= 1; # 10

    

    sclk <= 0; # 10
    sclk <= 1; # 10

    

    sclk <= 0; # 10
    sclk <= 1; # 10

    

    sclk <= 0; # 10
    sclk <= 1; # 10

    

    sclk <= 0; # 10
    sclk <= 1; # 10

    

    sclk <= 0; # 10
    sclk <= 1; # 10

    

    sclk <=0; # 10
    sclk = 1; # 10

    

    sclk <= 0; # 10
    sclk <= 1; # 10

    

    sclk <= 0; # 10
    sclk <= 1; # 10

    

    sclk <= 0; # 10
    sclk <= 1; # 10

     

    sclk <= 0; # 10
    sclk <= 1; # 10

    

    sclk <= 0; # 10
    sclk <= 1; # 10

    

    sclk <= 0; # 10
    sclk <= 1; # 10

    

    sclk <= 0; # 10
    sclk <= 1; # 10

    

    sclk <= 0; # 10
    sclk <= 1; # 10

    

    sclk <= 0; 
    cs <=1; #10
    sclk <= 1; # 10

    


    sclk <= 0; # 10
    sclk <= 1; # 10

    sclk <= 0; # 10
    sclk <= 1; # 10

    //READ OP TESTING

    $display("Read op testing");

    shiftRegOut0 <= 1; 

    sclk <= 0; 
    cs <= 0; # 10
    sclk = 1; # 10
    

    sclk <= 0; # 10
    sclk <= 1; # 10

    

    sclk <= 0; # 10
    sclk <= 1; # 10

    

    sclk <= 0; # 10
    sclk <= 1; # 10

    

    sclk <= 0; # 10
    sclk <= 1; # 10

    

    sclk <= 0; # 10
    sclk <= 1; # 10

    

    sclk <= 0; # 10
    sclk <= 1; # 10

    

    sclk <=0; # 10
    sclk = 1; # 10

    

    sclk <= 0; # 10
    sclk <= 1; # 10

    

    sclk <= 0; # 10
    sclk <= 1; # 10

    

    sclk <= 0; # 10
    sclk <= 1; # 10

     

    sclk <= 0; # 10
    sclk <= 1; # 10

    

    sclk <= 0; # 10
    sclk <= 1; # 10

    

    sclk <= 0; # 10
    sclk <= 1; # 10

    

    sclk <= 0; # 10
    sclk <= 1; # 10

    

    sclk <= 0; # 10
    sclk <= 1; # 10

    

    sclk <= 0; 
    cs <=1; #10
    sclk <= 1; # 10

    

    $finish; 

    end
    endmodule

fsm.vcd
$date
	Sat Oct 27 15:33:38 2018
$end
$version
	Icarus Verilog
$end
$timescale
	1s
$end
$scope module testfsm $end
$var wire 5 ! counter [4:0] $end
$var wire 1 " add_WE $end
$var wire 1 # SR_WE $end
$var wire 1 $ MISO_Buff $end
$var wire 1 % DM_WE $end
$var reg 1 & cs $end
$var reg 1 ' sclk $end
$var reg 1 ( shiftRegOut0 $end
$scope module fsm1 $end
$var wire 1 & cs $end
$var wire 1 ' sclk $end
$var wire 1 ( shiftRegOut0 $end
$var reg 1 % DM_WE $end
$var reg 1 $ MISO_Buff $end
$var reg 1 # SR_WE $end
$var reg 1 " add_WE $end
$var reg 5 ) counter [4:0] $end
$var reg 3 * state [2:0] $end
$upscope $end
$upscope $end
$enddefinitions $end
#0
$dumpvars
b101 *
b0 )
1(
0'
1&
0%
0$
0#
0"
b0 !
$end
#10
b0 !
b0 )
1'
#20
0&
0'
0(
#30
b1 !
b1 )
1'
#40
0'
#50
b10 !
b10 )
1'
#60
0'
#70
b11 !
b11 )
1'
#80
0'
#90
b100 !
b100 )
1'
#100
0'
#110
b101 !
b101 )
1'
#120
0'
#130
b110 !
b110 )
1'
#140
0'
#150
b111 !
b111 )
b0 *
1'
#160
0'
#170
b11 *
b0 !
b0 )
1"
1'
#180
0'
#190
b1 !
b1 )
0"
1'
#200
0'
#210
b10 !
b10 )
1'
#220
0'
#230
b11 !
b11 )
1'
#240
0'
#250
b100 !
b100 )
1'
#260
0'
#270
b101 !
b101 )
1'
#280
0'
#290
b110 !
b110 )
1'
#300
0'
#310
b100 *
b111 !
b111 )
1'
#320
0'
#330
b101 *
b1000 !
b1000 )
1%
1'
#340
1&
0'
#350
b0 !
b0 )
0%
1'
#360
0'
#370
b0 !
b0 )
1'
#380
0'
#390
b0 !
b0 )
1'
#400
0&
0'
1(
#410
b1 !
b1 )
1'
#420
0'
#430
b10 !
b10 )
1'
#440
0'
#450
b11 !
b11 )
1'
#460
0'
#470
b100 !
b100 )
1'
#480
0'
#490
b101 !
b101 )
1'
#500
0'
#510
b110 !
b110 )
1'
#520
0'
#530
b111 !
b111 )
b0 *
1'
#540
0'
#550
b1 *
b1000 !
b1000 )
1"
1'
#560
0'
#570
b10 *
b0 !
b0 )
1#
0"
1'
#580
0'
#590
b1 !
b1 )
1$
0#
1'
#600
0'
#610
b10 !
b10 )
1'
#620
0'
#630
b11 !
b11 )
1'
#640
0'
#650
b100 !
b100 )
1'
#660
0'
#670
b101 !
b101 )
1'
#680
0'
#690
b110 !
b110 )
1'
#700
0'
#710
b111 !
b111 )
1'
#720
1&
0'
#730
b101 *
b0 !
b0 )
1'
