inputconditioner.v
//------------------------------------------------------------------------
// Input Conditioner
//    1) Synchronizes input to clock domain
//    2) Debounces input
//    3) Creates pulses at edge transitions
//------------------------------------------------------------------------

module inputconditioner
(
input 	    clk,            // Clock domain to synchronize input to
input	    noisysignal,    // (Potentially) noisy input signal
output reg  conditioned,    // Conditioned output signal
output reg  positiveedge,   // 1 clk pulse at rising edge of conditioned
output reg  negativeedge    // 1 clk pulse at falling edge of conditioned
);

    parameter counterwidth = 3; // Counter size, in bits, >= log2(waittime)
    parameter waittime = 3;     // Debounce delay, in clock cycles
    
    reg[counterwidth-1:0] counter = 0;
    reg synchronizer0 = 0;
    reg synchronizer1 = 0;

    always @(posedge clk ) begin
        
        if(conditioned == synchronizer1) begin
            counter <= 0;
            // Reset edge detect
            positiveedge <= 0;
            negativeedge <= 0;
        end
        else begin
            if( counter == waittime) begin
                counter <= 0;
                // Signal about to go through d flip flop. Now is the time to look at 
                if (synchronizer1 == 1 && conditioned == 0)
                    positiveedge <= 1;
                if (synchronizer1 == 0 && conditioned == 1)
                    negativeedge <= 1;
                conditioned <= synchronizer1;
            end
            else 
                counter <= counter+1;
        end

        synchronizer0 <= noisysignal;
        synchronizer1 <= synchronizer0;

    end

endmodule

inputconditioner.t.v
//------------------------------------------------------------------------
// Input Conditioner test bench
//------------------------------------------------------------------------

`timescale 1 ns / 1 ps
`include "inputconditioner.v"

module testConditioner();

    reg clk;
    reg pin;
    wire conditioned;
    wire rising;
    wire falling;
    
    inputconditioner dut(.clk(clk),
    			 .noisysignal(pin),
			 .conditioned(conditioned),
			 .positiveedge(rising),
			 .negativeedge(falling));


    // Generate clock (50MHz)
    initial clk=0;
    always # 10 clk=!clk;    // 50MHz Clock

    
    initial begin

       $dumpfile("inputconditioner.vcd");
       $dumpvars();

       // Testing noisy low & high signals: Concerned if "conditioned" switches during noise or doesn't switch after noise

        pin = 0; # 1000 
        pin = 1; # 5
        pin = 0; # 3
        pin = 1; # 5
        if (conditioned == 1)
            $display("Conditioned high and should not be high");
        pin = 0; # 3
        pin = 1; # 1000        
        if (conditioned != 1)
            $display("Conditioned not high and should be high");
        pin = 0; # 3
        pin = 1; # 5
        pin = 0; # 3
        if (conditioned == 0)
            $display("Conditioned low and should not be low");
        pin = 1; # 5
        pin = 0; # 1000
        if (conditioned != 0)
            $display("Conditioned not low and should be low");

        // Testing edge detection: Concerned if pos/neg edges do not go high and "conditioned" switches. 
        // Or concerned if pos/neg edges go high and "conditioned" didn't switch

        pin = 1; # 30
        pin = 0; # 30
        pin = 1; # 300
        pin = 0; # 300
        pin = 1; # 300
        pin = 0; # 100
        pin = 1; # 100
        pin = 0; # 100
        
        // Testing synchronization: Concerned if pos/neg edges switch high while clock is low
        pin = 1; # 253
        pin = 0; # 166
        pin = 1; # 324
        pin = 0; # 383

        $finish();
   end 

// For testing edge detection
   always @ (posedge falling) begin
       if(conditioned != 0)
            $display("Falling flagged but conditioned not 0");
   end
   always @ (posedge rising) begin
       if(conditioned != 1)
            $display("Rising flagged but conditioned not 1");
   end
   always @ (posedge conditioned) begin
        if(falling == 1)
            $display("Falling flagged when condition rising");
        if(rising == 0)
            $display("Rising not flagged when conditin rising");
   end
   always @ (negedge conditioned) begin
        if(falling == 0)
            $display("Flling not flagged when condition falling");
        if(rising == 1)
            $display("Rising flagged when conditin falling");
   end

// For testing synchronization
   always @ (posedge falling) begin
       if(clk == 0)
            $display("Falling not synchronized");
   end
   always @ (posedge rising) begin
       if(clk == 0)
            $display("Rising not synchronized");
   end
    
endmodule

inputconditioner.vcd
$date
	Mon Oct 29 20:05:14 2018
$end
$version
	Icarus Verilog
$end
$timescale
	1ps
$end
$scope module testConditioner $end
$var wire 1 ! rising $end
$var wire 1 " falling $end
$var wire 1 # conditioned $end
$var reg 1 $ clk $end
$var reg 1 % pin $end
$scope module dut $end
$var wire 1 $ clk $end
$var wire 1 % noisysignal $end
$var reg 1 # conditioned $end
$var reg 3 & counter [2:0] $end
$var reg 1 " negativeedge $end
$var reg 1 ! positiveedge $end
$var reg 1 ' synchronizer0 $end
$var reg 1 ( synchronizer1 $end
$upscope $end
$upscope $end
$enddefinitions $end
#0
$dumpvars
0(
0'
b0 &
0%
0$
x#
x"
x!
$end
#10000
b1 &
1$
#20000
0$
#30000
b10 &
1$
#40000
0$
#50000
b11 &
1$
#60000
0$
#70000
0#
b0 &
1$
#80000
0$
#90000
0"
0!
1$
#100000
0$
#110000
1$
#120000
0$
#130000
1$
#140000
0$
#150000
1$
#160000
0$
#170000
1$
#180000
0$
#190000
1$
#200000
0$
#210000
1$
#220000
0$
#230000
1$
#240000
0$
#250000
1$
#260000
0$
#270000
1$
#280000
0$
#290000
1$
#300000
0$
#310000
1$
#320000
0$
#330000
1$
#340000
0$
#350000
1$
#360000
0$
#370000
1$
#380000
0$
#390000
1$
#400000
0$
#410000
1$
#420000
0$
#430000
1$
#440000
0$
#450000
1$
#460000
0$
#470000
1$
#480000
0$
#490000
1$
#500000
0$
#510000
1$
#520000
0$
#530000
1$
#540000
0$
#550000
1$
#560000
0$
#570000
1$
#580000
0$
#590000
1$
#600000
0$
#610000
1$
#620000
0$
#630000
1$
#640000
0$
#650000
1$
#660000
0$
#670000
1$
#680000
0$
#690000
1$
#700000
0$
#710000
1$
#720000
0$
#730000
1$
#740000
0$
#750000
1$
#760000
0$
#770000
1$
#780000
0$
#790000
1$
#800000
0$
#810000
1$
#820000
0$
#830000
1$
#840000
0$
#850000
1$
#860000
0$
#870000
1$
#880000
0$
#890000
1$
#900000
0$
#910000
1$
#920000
0$
#930000
1$
#940000
0$
#950000
1$
#960000
0$
#970000
1$
#980000
0$
#990000
1$
#1000000
0$
1%
#1005000
0%
#1008000
1%
#1010000
1'
1$
#1013000
0%
#1016000
1%
#1020000
0$
#1030000
1(
1$
#1040000
0$
#1050000
b1 &
1$
#1060000
0$
#1070000
b10 &
1$
#1080000
0$
#1090000
b11 &
1$
#1100000
0$
#1110000
1#
1!
b0 &
1$
#1120000
0$
#1130000
0!
1$
