shiftregister.v
//------------------------------------------------------------------------
// Shift Register
//   Parameterized width (in bits)
//   Shift register can operate in two modes:
//      - serial in, parallel out
//      - parallel in, serial out
//------------------------------------------------------------------------

module shiftregister
#(parameter width = 8)
(
input               clk,                // FPGA Clock
input               peripheralClkEdge,  // Edge indicator
input               parallelLoad,       // 1 = Load shift reg with parallelDataIn
input  [width-1:0]  parallelDataIn,     // Load shift reg in parallel
input               serialDataIn,       // Load shift reg serially
output [width-1:0]  parallelDataOut,    // Shift reg data contents
output              serialDataOut       // Positive edge synchronized
);

    reg [width-1:0]      shiftregistermem;
    assign serialDataOut = shiftregistermem[width-1];
    assign parallelDataOut = shiftregistermem;
    always @(posedge clk) begin
      if (parallelLoad ==1) begin
        shiftregistermem <= parallelDataIn;
      end
      else if (peripheralClkEdge == 1) begin
        shiftregistermem = shiftregistermem<<1;
        shiftregistermem[0] = serialDataIn;
      end
    end

endmodule

shiftregister.t.v
//------------------------------------------------------------------------
// Shift Register test bench
//------------------------------------------------------------------------
`include "shiftregister.v"

module testshiftregister();

    reg             clk;
    reg             peripheralClkEdge;
    reg             parallelLoad;
    wire[7:0]       parallelDataOut;
    wire            serialDataOut;
    reg[7:0]        parallelDataIn;
    reg             serialDataIn;

    // Instantiate with parameter width = 8
    shiftregister #(8) dut(.clk(clk),
    		           .peripheralClkEdge(peripheralClkEdge),
    		           .parallelLoad(parallelLoad),
    		           .parallelDataIn(parallelDataIn),
    		           .serialDataIn(serialDataIn),
    		           .parallelDataOut(parallelDataOut),
    		           .serialDataOut(serialDataOut));
    //shiftregister #(8) dut (clk,peripheralClkEdge,parallelLoad,parallelDataOut,serialDataOut,parallelDataIn,serialDataIn);
    reg dutpassed;
    initial begin
    //running test for serial loading with 0 serial data out


    $dumpfile("shift.vcd"); //Creating .vcd file for timing analysis
    $dumpvars;

    parallelLoad = 0;
    parallelDataIn = 8'd16;
    peripheralClkEdge = 1;

    #5 clk = 0; #5 clk = 1;
    serialDataIn = 1;
    #5 clk = 0; #5 clk = 1;
    serialDataIn = 0;
    peripheralClkEdge = 0;
    #5 clk = 0; #5 clk = 1;
    peripheralClkEdge = 1;
    #5 clk = 0; #5 clk = 1;
    #5 clk = 0; #5 clk = 1;
    serialDataIn = 0;
    #5 clk = 0; #5 clk = 1;
    serialDataIn = 1;
    #5 clk = 0; #5 clk = 1;
    #5 clk = 0; #5 clk = 1;
    serialDataIn = 1;
    #5 clk = 0; #5 clk = 1;
    #5 clk = 0; #5 clk = 1;

    //testing for 1 serial out and serial loading
    if((parallelDataOut !== 8'b10001111) || (serialDataOut !== 1)) begin
      dutpassed = 0;
      $display("Test Case 1 Failed");
      $display("%b  |  %b", parallelDataOut, serialDataOut);
    end

    //running test for serial loading with 0 serial data out
    parallelLoad = 0;
    parallelDataIn = 8'd16;
    serialDataIn = 1;
    peripheralClkEdge = 1;

    #5 clk = 0; #5 clk = 1;
    serialDataIn = 0;
    #5 clk = 0; #5 clk = 1;
    serialDataIn = 1;
    peripheralClkEdge = 0;
    #5 clk = 0; #5 clk = 1;
    peripheralClkEdge = 1;
    #5 clk = 0; #5 clk = 1;
    #5 clk = 0; #5 clk = 1;
    serialDataIn = 0;
    #5 clk = 0; #5 clk = 1;
    #5 clk = 0; #5 clk = 1;
    #5 clk = 0; #5 clk = 1;
    serialDataIn = 1;
    #5 clk = 0; #5 clk = 1;
    #5 clk = 0; #5 clk = 1;

    //testing for 0 serial out and serial loading
    if((parallelDataOut !== 8'b01100011) || (serialDataOut !== 0)) begin
      dutpassed = 0;
      $display("Test Case 2 Failed");
      $display("%b  |  %b", parallelDataOut, serialDataOut);
    end


    //setup for 0 serial out and parallel loading
    parallelLoad = 1;
    parallelDataIn = 8'd16;
    #10 peripheralClkEdge = 0; #10 peripheralClkEdge = 1; #10
    #5 clk = 0; #5 clk = 1; #5 clk = 0; #5 clk = 1; #5 clk = 0; #5 clk = 1;
    #5 clk = 0; #5 clk = 1; #5 clk = 0; #5 clk = 1; #5 clk = 0; #5 clk = 1;
    #5 clk = 0; #5 clk = 1; #5 clk = 0; #5 clk = 1; #5 clk = 0; #5 clk = 1;

    //testing for 0 serial out and parallel loading
    if((parallelDataOut !== 8'b00010000) || (serialDataOut !== 0)) begin
      dutpassed = 0;
      $display("Test Case 3 Failed");
      $display("%b  |  %b", parallelDataOut, serialDataOut);
    end


    //setting up for 1 serial out and parallel loading
    parallelDataIn = 8'd128;
    parallelLoad = 1;
    #10 peripheralClkEdge = 0; #10 peripheralClkEdge = 1; #10
    #5 clk = 0; #5 clk = 1; #5 clk = 0; #5 clk = 1; #5 clk = 0; #5 clk = 1;
    #5 clk = 0; #5 clk = 1; #5 clk = 0; #5 clk = 1; #5 clk = 0; #5 clk = 1;
    #5 clk = 0; #5 clk = 1; #5 clk = 0; #5 clk = 1; #5 clk = 0; #5 clk = 1;

    //testing for 0 serial out and parallel loading
    if((parallelDataOut !== 8'b10000000) || (serialDataOut !== 1)) begin
      dutpassed = 0;
      $display("Test Case 4 Failed");
      $display("%b  |  %b", parallelDataOut, serialDataOut);
    end

    //testing 0 edge case (parallel loading)

    //setting up for 0 serial out and parallel loading
    parallelDataIn = 8'd0;
    parallelLoad = 1;
    #10 peripheralClkEdge = 0; #10 peripheralClkEdge = 1; #10
    #5 clk = 0; #5 clk = 1; #5 clk = 0; #5 clk = 1; #5 clk = 0; #5 clk = 1;
    #5 clk = 0; #5 clk = 1; #5 clk = 0; #5 clk = 1; #5 clk = 0; #5 clk = 1;
    #5 clk = 0; #5 clk = 1; #5 clk = 0; #5 clk = 1; #5 clk = 0; #5 clk = 1;

    //testing for 0 serial out and parallel loading
    if((parallelDataOut !== 8'b00000000) || (serialDataOut !== 0)) begin
      dutpassed = 0;
      $display("Test Case 5(Zeros Parallel Loading) Failed");
      $display("%b  |  %b", parallelDataOut, serialDataOut);
    end

    //running test for serial loading with 0 serial data out
    parallelLoad = 0;
    parallelDataIn = 8'd101;
    serialDataIn = 0;
    peripheralClkEdge = 1;
    #5 clk = 0; #5 clk = 1; #5 clk = 0; #5 clk = 1; #5 clk = 0; #5 clk = 1;
    #5 clk = 0; #5 clk = 1; #5 clk = 0; #5 clk = 1; #5 clk = 0; #5 clk = 1;
    #5 clk = 0; #5 clk = 1; #5 clk = 0; #5 clk = 1; #5 clk = 0; #5 clk = 1;

    //testing for 0 serial out and serial loading
    if((parallelDataOut !== 8'b00000000) || (serialDataOut !== 0)) begin
      dutpassed = 0;
      $display("Test Case 6 (Zeros Serial Loading) Failed");
      $display("%b  |  %b", parallelDataOut, serialDataOut);
    end


    //testing 0 edge case (parallel loading)

    //setting up for 0 serial out and parallel loading
    parallelDataIn = 8'd255;
    parallelLoad = 1;
    #10 peripheralClkEdge = 0; #10 peripheralClkEdge = 1; #10
    #5 clk = 0; #5 clk = 1; #5 clk = 0; #5 clk = 1; #5 clk = 0; #5 clk = 1;
    #5 clk = 0; #5 clk = 1; #5 clk = 0; #5 clk = 1; #5 clk = 0; #5 clk = 1;
    #5 clk = 0; #5 clk = 1; #5 clk = 0; #5 clk = 1; #5 clk = 0; #5 clk = 1;

    //testing for 0 serial out and parallel loading
    if((parallelDataOut !== 8'b11111111) || (serialDataOut !== 1)) begin
      dutpassed = 0;
      $display("Test Case 5(Zeros Parallel Loading) Failed");
      $display("%b  |  %b", parallelDataOut, serialDataOut);
    end

    //running test for serial loading with 1 serial data out
    parallelLoad = 0;
    parallelDataIn = 8'd101;
    serialDataIn = 1;
    peripheralClkEdge = 1;
    #5 clk = 0; #5 clk = 1; #5 clk = 0; #5 clk = 1; #5 clk = 0; #5 clk = 1;
    #5 clk = 0; #5 clk = 1; #5 clk = 0; #5 clk = 1; #5 clk = 0; #5 clk = 1;
    #5 clk = 0; #5 clk = 1; #5 clk = 0; #5 clk = 1; #5 clk = 0; #5 clk = 1;

    //testing for 1 serial out and serial loading
    if((parallelDataOut !== 8'b11111111) || (serialDataOut !== 1)) begin
      dutpassed = 0;
      $display("Test Case 6 (Zeros Serial Loading) Failed");
      $display("%b  |  %b", parallelDataOut, serialDataOut);
    end

    $finish();

    end

endmodule

shift.vcd
$date
	Mon Oct 29 18:16:53 2018
$end
$version
	Icarus Verilog
$end
$timescale
	1s
$end
$scope module testshiftregister $end
$var wire 1 ! serialDataOut $end
$var wire 8 " parallelDataOut [7:0] $end
$var reg 1 # clk $end
$var reg 1 $ dutpassed $end
$var reg 8 % parallelDataIn [7:0] $end
$var reg 1 & parallelLoad $end
$var reg 1 ' peripheralClkEdge $end
$var reg 1 ( serialDataIn $end
$scope module dut $end
$var wire 1 # clk $end
$var wire 8 ) parallelDataIn [7:0] $end
$var wire 8 * parallelDataOut [7:0] $end
$var wire 1 & parallelLoad $end
$var wire 1 ' peripheralClkEdge $end
$var wire 1 ( serialDataIn $end
$var wire 1 ! serialDataOut $end
$var reg 8 + shiftregistermem [7:0] $end
$upscope $end
$upscope $end
$enddefinitions $end
#0
$dumpvars
bx +
bx *
b10000 )
x(
1'
0&
b10000 %
x$
x#
bx "
x!
$end
#5
0#
#10
bx1 "
bx1 *
bx1 +
1(
1#
#15
0#
#20
0'
0(
1#
#25
0#
#30
bx10 "
bx10 *
bx10 +
1'
1#
#35
0#
#40
bx100 "
bx100 *
bx100 +
1#
#45
0#
#50
bx1000 "
bx1000 *
bx1000 +
1#
#55
0#
#60
bx10001 "
bx10001 *
bx10001 +
1(
1#
#65
0#
#70
bx100011 "
bx100011 *
bx100011 +
1#
#75
0#
#80
bx1000111 "
bx1000111 *
bx1000111 +
1#
#85
0#
#90
1!
b10001111 "
b10001111 *
b10001111 +
1#
#95
0#
#100
0!
b11111 "
b11111 *
b11111 +
1#
#105
0#
#110
b111110 "
b111110 *
b111110 +
0(
1#
#115
0#
#120
0'
1(
1#
#125
0#
#130
b1111101 "
b1111101 *
b1111101 +
1'
1#
#135
0#
#140
1!
b11111011 "
b11111011 *
b11111011 +
1#
#145
0#
#150
b11110110 "
b11110110 *
b11110110 +
0(
1#
#155
0#
#160
b11101100 "
b11101100 *
b11101100 +
1#
#165
0#
#170
b11011000 "
b11011000 *
b11011000 +
1#
#175
0#
#180
b10110001 "
b10110001 *
b10110001 +
1(
1#
#185
0#
#190
0!
b1100011 "
b1100011 *
b1100011 +
1#
#195
0#
#200
b10000 "
b10000 *
b10000 +
1&
1#
#210
0'
#220
1'
#235
0#
#240
1#
#245
0#
#250
1#
#255
0#
#260
1#
#265
0#
#270
1#
#275
0#
#280
1#
#285
0#
#290
1#
#295
0#
#300
1#
#305
0#
#310
1#
#315
0#
#320
1!
b10000000 "
b10000000 *
b10000000 +
b10000000 %
b10000000 )
1#
#330
0'
#340
1'
#355
0#
#360
1#
#365
0#
#370
1#
#375
0#
#380
1#
#385
0#
#390
1#
#395
0#
#400
1#
#405
0#
#410
1#
#415
0#
#420
1#
#425
0#
#430
1#
#435
0#
#440
0!
b0 "
b0 *
b0 +
b0 %
b0 )
1#
#450
0'
#460
1'
#475
0#
#480
1#
#485
0#
#490
1#
#495
0#
#500
1#
#505
0#
#510
1#
#515
0#
#520
1#
#525
0#
#530
1#
#535
0#
#540
1#
#545
0#
#550
1#
#555
0#
#560
0(
b1100101 %
b1100101 )
0&
1#
#565
0#
#570
1#
#575
0#
#580
1#
#585
0#
#590
1#
#595
0#
#600
1#
#605
0#
#610
1#
#615
0#
#620
1#
#625
0#
#630
1#
#635
0#
#640
1#
#645
0#
#650
1!
b11111111 "
b11111111 *
b11111111 +
1&
b11111111 %
b11111111 )
1#
#660
0'
#670
1'
#685
0#
#690
1#
#695
0#
#700
1#
#705
0#
#710
1#
#715
0#
#720
1#
#725
0#
#730
1#
#735
0#
#740
1#
#745
0#
#750
1#
#755
0#
#760
1#
#765
0#
#770
b11111111 "
b11111111 *
b11111111 +
1(
b1100101 %
b1100101 )
0&
1#
#775
0#
#780
b11111111 "
b11111111 *
b11111111 +
1#
#785
0#
#790
b11111111 "
b11111111 *
b11111111 +
1#
#795
0#
#800
b11111111 "
b11111111 *
b11111111 +
1#
#805
0#
#810
b11111111 "
b11111111 *
b11111111 +
1#
#815
0#
#820
b11111111 "
b11111111 *
b11111111 +
1#
#825
0#
#830
b11111111 "
b11111111 *
b11111111 +
1#
#835
0#
#840
b11111111 "
b11111111 *
b11111111 +
1#
#845
0#
#850
b11111111 "
b11111111 *
b11111111 +
1#
#855
0#
#860
b11111111 "
b11111111 *
b11111111 +
1#
