inputWave.v
module inputWave
(
  input[15:0] dataIn,
  input sclk,
  input enable,
  output reg dataOut,
  output reg actualCS
  );
  reg[4:0] pos;
  initial pos = 4'd15;
always @(negedge sclk)begin
  actualCS = enable;
  dataOut = dataIn[pos];
  $display("On bit %b which equals %b", pos, dataIn[pos]);
  if (actualCS == 0)begin
    pos = pos - 1;
    end
  if (pos == 0000 && actualCS == 0)begin
    pos = 4'd15;
   end
end

endmodule

fsm.v
`define ADDRESS 3'd00
`define MISO_REG 3'd1
`define MISO_OUT 3'd2
`define MOSI_MEM 3'd3
`define MOSI_WRI 3'd4
`define OFF 3'd5
module fsm
(
  input  cs,
  input clk,
  input sclk,
  input  shiftRegOut0,
  output add_WE,
  output DM_WE,
  output SR_WE,
  output MISO_Buff
  );
      reg[2:0] state;
      initial state = `OFF;
      parameter waittime = 7;
      reg[4:0] counter;
      initial counter <= 0;
      reg miOut, moMem, turnOn;
      reg add_WE, DM_WE, SR_WE, MISO_Buff;

      always @(posedge sclk) begin
        if( counter == waittime) begin
            counter <= 0;
        end
        else begin
            counter <= counter+1;
        end
      end

      always @(posedge sclk) begin
      $display("Positive sclk edge");
      if (cs)begin
        state <= `OFF;
        turnOn <= 0;
        $display("In state OFF");
      end

      else if (cs == 0 && state==`OFF)begin
        if (turnOn == 0)begin
          counter = 0;
          turnOn = 1;
          $display("Turn on = %b",turnOn);
        end
        $display("In state OFF going to address");
        if (counter == waittime)begin
          state = `ADDRESS;
          $display("counter: %b",counter);
        end
        $display("counter: %b",counter);
      end

      else if (state == `ADDRESS && shiftRegOut0 == 1)begin
        state <= `MISO_REG;
        $display("In state ADDRESS going to miso_reg");
      end

      else if (state == `MISO_REG)begin
        state <= `MISO_OUT;
        miOut <= 0;
        $display("In state going to miso_out");
      end

      else if (state == `MISO_OUT)begin
        if (miOut == 0)begin
          counter <= 0;
          miOut <= 1;
          $display("In state of miso_out");
        end
        if (counter == waittime)
          state <= `OFF;
      end

      else if (state == `ADDRESS && shiftRegOut0 == 0)begin
        state <= `MOSI_MEM;
        moMem <= 0;
        $display("In state ADDRESS going to mosimem");
      end

      else if(state == `MOSI_MEM)begin
        $display("In state of mosimem");
        if (moMem == 0) begin
          moMem = 1;
          counter = 0;
          $display("MOSI counter: %b",counter);
        end
        if (counter == waittime-1)
          state <= `MOSI_WRI;
          $display("MOSI counter: %b",counter);
      end

      else if (state == `MOSI_WRI)begin
        $display("In state mosi_wri");
        state <= `OFF;
      end
      end

  always @(posedge sclk) begin
  case (state)
    `ADDRESS:   begin add_WE <= 1; DM_WE<=0; SR_WE <= 0; MISO_Buff <= 0; end
    `MISO_REG:  begin add_WE <= 0; DM_WE<=0; SR_WE <= 1; MISO_Buff <= 0; end
    `MOSI_MEM:  begin add_WE <= 0; DM_WE<=0; SR_WE <= 0; MISO_Buff <= 0; end
    `MISO_OUT:  begin add_WE <= 0; DM_WE<=0; SR_WE <= 0; MISO_Buff <= 1; end
    `MOSI_WRI:  begin add_WE <= 0; DM_WE<=1; SR_WE <= 0; MISO_Buff <= 0; end
    `OFF:       begin add_WE <= 0; DM_WE<=0; SR_WE <= 0; MISO_Buff <= 0; end
  endcase
  end

  endmodule

spimemory.v
//------------------------------------------------------------------------
// SPI Memory
//------------------------------------------------------------------------

`include "shiftregister.v"
`include "inputconditioner.v"
`include "datamemory.v"
`include "fsm.v"


module dff #( parameter W = 8)
(
    input clk,
    input enable,
    input      [W-1:0] d,
    output reg [W-1:0] q
);
    always @(posedge clk) begin
        if(enable) begin
            q <= d;
        end
    end
endmodule

module spiMemory
(
    input           clk,        // FPGA clock
    input           sclk_pin,   // SPI clock
    input           cs_pin,     // SPI chip select
    output          miso_pin,   // SPI master in slave out
    input           mosi_pin,   // SPI master out slave in
    output [3:0]    leds        // LEDs for debugging
);

	wire mosi_cond, mosi_pos, mosi_neg, sclk_cond, sclk_pos, sclk_neg, cs_cond, cs_pos, cs_neg;
    wire miso_bufe, dm_we, addr_we, sr_we;
    wire[7:0] shiftRegOutP, dataMemOut, addressLatchOut;
    wire[6:0] address;
    wire shiftRegOutS, misoPreBufe;

    assign address = addressLatchOut[6:0];

    inputconditioner ic0 (.clk(clk),
    					.noisysignal(mosi_pin),
    					.conditioned(mosi_cond),
    					.positiveedge(mosi_pos),
    					.negativeedge(mosi_neg));
    inputconditioner ic1 (.clk(clk),
    					.noisysignal(sclk_pin),
    					.conditioned(sclk_cond),
    					.positiveedge(sclk_pos),
    					.negativeedge(sclk_neg));
    inputconditioner ic2 (.clk(clk),
    					.noisysignal(cs_pin),
    					.conditioned(cs_cond),
    					.positiveedge(cs_pos),
    					.negativeedge(cs_neg));
	shiftregister #(8) dut(.clk(clk),
    		           .peripheralClkEdge(sclk_pos),
     		           .parallelLoad(sr_we),
     		           .parallelDataIn(dataMemOut),
     		           .serialDataIn(mosi_cond),
     		           .parallelDataOut(shiftRegOutP),
     		           .serialDataOut(shiftRegOutS));
	datamemory data_mem(.clk(clk),
    					.dataOut(dataMemOut),
    					.address(address),	// MSB OF INPUT BECOMES DM_WE
    					.writeEnable(dm_we),
   						.dataIn(shiftRegOutP));
	dff #(1) miso_buff (.clk(clk),
						.enable(sclk_neg),
						.d(shiftRegOutS),
						.q(misoPreBufe));
	dff #(8) addr_latch(.clk(clk),
						.enable(addr_we),
						.d(shiftRegOutP),
						.q(addressLatchOut));

	fsm finite_state_m (.cs(cs_cond),
						.clk(clk),
						.sclk(sclk_cond),
						.shiftRegOut0(shiftRegOutP[0]),
						.add_WE(addr_we),
						.DM_WE(dm_we),
						.SR_WE(sr_we),
						.MISO_Buff(miso_bufe));

	// bufif1(out, in, control)
	//           control
	// in |      0 1 x z
	// -----------------
	// 0  |      z 0 L L
	// 1  |      z 1 H H
	// x  |      z x x x
	// z  |      z x x x
	// L means that output has 0 or z value. H means that output has 1 or z value.
	// x represents an unknown logic value. z represents high impedance logic value.
	bufif1 miso_buffer(miso_pin, misoPreBufe, miso_bufe);

endmodule

datamemory.v
//------------------------------------------------------------------------
// Data Memory
//   Positive edge triggered
//   dataOut always has the value mem[address]
//   If writeEnable is true, writes dataIn to mem[address]
//------------------------------------------------------------------------

module datamemory
#(
    parameter addresswidth  = 7,
    parameter depth         = 2**addresswidth,
    parameter width         = 8
)
(
    input 		                clk,
    output reg [width-1:0]      dataOut,
    input [addresswidth-1:0]    address,
    input                       writeEnable,
    input [width-1:0]           dataIn
);


    reg [width-1:0] memory [depth-1:0];

    always @(posedge clk) begin
        if(writeEnable)begin
            $display("Write Enable: %b",writeEnable);
            memory[address] <= dataIn;
            end
        dataOut <= memory[address];
    end

endmodule

shiftregister.v
//------------------------------------------------------------------------
// Shift Register
//   Parameterized width (in bits)
//   Shift register can operate in two modes:
//      - serial in, parallel out
//      - parallel in, serial out
//------------------------------------------------------------------------

module shiftregister
#(parameter width = 8)
(
input               clk,                // FPGA Clock
input               peripheralClkEdge,  // Edge indicator
input               parallelLoad,       // 1 = Load shift reg with parallelDataIn
input  [width-1:0]  parallelDataIn,     // Load shift reg in parallel
input               serialDataIn,       // Load shift reg serially
output [width-1:0]  parallelDataOut,    // Shift reg data contents
output              serialDataOut       // Positive edge synchronized
);

    reg [width-1:0]      shiftregistermem;
    assign serialDataOut = shiftregistermem[width-1];
    assign parallelDataOut = shiftregistermem;
    always @(posedge clk) begin
      if (parallelLoad ==1) begin
        shiftregistermem <= parallelDataIn;
      end
      else if (peripheralClkEdge == 1) begin
        shiftregistermem = shiftregistermem<<1;
        shiftregistermem[0] = serialDataIn;

        $display("Shift Register address: %b",shiftregistermem);

      end
    end

endmodule

inputconditioner.v
//------------------------------------------------------------------------
// Input Conditioner
//    1) Synchronizes input to clock domain
//    2) Debounces input
//    3) Creates pulses at edge transitions
//------------------------------------------------------------------------

module inputconditioner
(
input 	    clk,            // Clock domain to synchronize input to
input	    noisysignal,    // (Potentially) noisy input signal
output reg  conditioned,    // Conditioned output signal
output reg  positiveedge,   // 1 clk pulse at rising edge of conditioned
output reg  negativeedge    // 1 clk pulse at falling edge of conditioned
);

    parameter counterwidth = 3; // Counter size, in bits, >= log2(waittime)
    parameter waittime = 3;     // Debounce delay, in clock cycles
    
    reg[counterwidth-1:0] counter = 0;
    reg synchronizer0 = 0;
    reg synchronizer1 = 0;

    always @(posedge clk ) begin
        
        if(conditioned == synchronizer1) begin
            counter <= 0;
            // Reset edge detect
            positiveedge <= 0;
            negativeedge <= 0;
        end
        else begin
            if( counter == waittime) begin
                counter <= 0;
                // Signal about to go through d flip flop. Now is the time to look at 
                if (synchronizer1 == 1 && conditioned == 0)
                    positiveedge <= 1;
                if (synchronizer1 == 0 && conditioned == 1)
                    negativeedge <= 1;
                conditioned <= synchronizer1;
            end
            else 
                counter <= counter+1;
        end

        synchronizer0 <= noisysignal;
        synchronizer1 <= synchronizer0;

    end

endmodule

spimemory.t.v

`include "spimemory.v"
`include "inputWave.v"



module spimemory_test();

	reg clk, sclk_pin, cs, mosi_pin;
	wire dataOut,cs_pin;
	always #10 clk = !clk;
	always #100 sclk_pin = !sclk_pin;
	wire miso_pin;
	wire[3:0] leds;
	parameter write_op = 16'b0101011011110101;
	parameter read_op = 8'b01010111;


	spiMemory dut(.clk(clk), .sclk_pin(sclk_pin), .cs_pin(cs_pin), .miso_pin(miso_pin), .mosi_pin(mosi_pin), .leds(leds));
	inputWave inWave(.dataIn(write_op),.sclk(sclk_pin),.enable(cs),.dataOut(dataOut),.actualCS(cs_pin));



	initial sclk_pin = 0;
	initial clk = 0;


	initial begin
    $dumpfile("spi.vcd"); //Creating .vcd file for timing analysis
    $dumpvars;

	cs <= 1;#200
	$display("STARTING NOW! Mosi=%b",dataOut);
	cs <= 0;#200
	mosi_pin <= dataOut;#100
	mosi_pin <= dataOut;#100
	mosi_pin <= dataOut;#100
	mosi_pin <= dataOut;#100
	mosi_pin <= dataOut;#100
	mosi_pin <= dataOut;#100
	mosi_pin <= dataOut;#100
	mosi_pin <= dataOut;#100
	mosi_pin <= dataOut;#100
	mosi_pin <= dataOut;#100
	mosi_pin <= dataOut;#100
	mosi_pin <= dataOut;#100
	mosi_pin <= dataOut;#100
	mosi_pin <= dataOut;#100
	mosi_pin <= dataOut;#100
	mosi_pin <= dataOut;#100
	mosi_pin <= dataOut;#100
	mosi_pin <= dataOut;#100
	mosi_pin <= dataOut;#100
	mosi_pin <= dataOut;#100
	mosi_pin <= dataOut;#100
	mosi_pin <= dataOut;#100
	mosi_pin <= dataOut;#100
	mosi_pin <= dataOut;#100
	mosi_pin <= dataOut;#100
	mosi_pin <= dataOut;#100
	mosi_pin <= dataOut;#100
	mosi_pin <= dataOut;#100
	mosi_pin <= dataOut;#100
	mosi_pin <= dataOut;#100
	mosi_pin <= dataOut;#100
	mosi_pin <= dataOut;#100
	mosi_pin <= dataOut;#100
	mosi_pin <= dataOut;#100
	mosi_pin <= dataOut;#100
	mosi_pin <= dataOut;#100
	mosi_pin <= dataOut;#100
	mosi_pin <= dataOut;#100
	$display("Address: %b",dut.data_mem.address);

	$finish;

	end

endmodule

spi.vcd
$date
	Tue Oct 23 18:48:51 2018
$end
$version
	Icarus Verilog
$end
$timescale
	1s
$end
$scope module spimemory_test $end
$var wire 4 ! leds [3:0] $end
$var wire 1 " miso_pin $end
$var wire 1 # dataOut $end
$var wire 1 $ cs_pin $end
$var reg 1 % clk $end
$var reg 1 & cs $end
$var reg 1 ' mosi_pin $end
$var reg 1 ( sclk_pin $end
$scope module dut $end
$var wire 1 % clk $end
$var wire 4 ) leds [3:0] $end
$var wire 1 " miso_pin $end
$var wire 1 ' mosi_pin $end
$var wire 1 ( sclk_pin $end
$var wire 1 * sr_we $end
$var wire 1 + shiftRegOutS $end
$var wire 8 , shiftRegOutP [7:0] $end
$var wire 1 - sclk_pos $end
$var wire 1 . sclk_neg $end
$var wire 1 / sclk_cond $end
$var wire 1 0 mosi_pos $end
$var wire 1 1 mosi_neg $end
$var wire 1 2 mosi_cond $end
$var wire 1 3 miso_bufe $end
$var wire 1 4 misoPreBufe $end
$var wire 1 5 dm_we $end
$var wire 8 6 dataMemOut [7:0] $end
$var wire 1 7 cs_pos $end
$var wire 1 $ cs_pin $end
$var wire 1 8 cs_neg $end
$var wire 1 9 cs_cond $end
$var wire 8 : addressLatchOut [7:0] $end
$var wire 7 ; address [6:0] $end
$var wire 1 < addr_we $end
$scope module addr_latch $end
$var wire 1 % clk $end
$var wire 1 < enable $end
$var wire 8 = d [7:0] $end
$var reg 8 > q [7:0] $end
$upscope $end
$scope module data_mem $end
$var wire 7 ? address [6:0] $end
$var wire 1 % clk $end
$var wire 1 5 writeEnable $end
$var wire 8 @ dataIn [7:0] $end
$var reg 8 A dataOut [7:0] $end
$upscope $end
$scope module dut $end
$var wire 1 % clk $end
$var wire 8 B parallelDataIn [7:0] $end
$var wire 8 C parallelDataOut [7:0] $end
$var wire 1 + serialDataOut $end
$var wire 1 2 serialDataIn $end
$var wire 1 - peripheralClkEdge $end
$var wire 1 * parallelLoad $end
$var reg 8 D shiftregistermem [7:0] $end
$upscope $end
$scope module finite_state_m $end
$var wire 1 % clk $end
$var wire 1 E shiftRegOut0 $end
$var wire 1 / sclk $end
$var wire 1 9 cs $end
$var reg 1 5 DM_WE $end
$var reg 1 3 MISO_Buff $end
$var reg 1 * SR_WE $end
$var reg 1 < add_WE $end
$var reg 5 F counter [4:0] $end
$var reg 1 G miOut $end
$var reg 1 H moMem $end
$var reg 3 I state [2:0] $end
$var reg 1 J turnOn $end
$upscope $end
$scope module ic0 $end
$var wire 1 % clk $end
$var wire 1 ' noisysignal $end
$var reg 1 2 conditioned $end
$var reg 3 K counter [2:0] $end
$var reg 1 1 negativeedge $end
$var reg 1 0 positiveedge $end
$var reg 1 L synchronizer0 $end
$var reg 1 M synchronizer1 $end
$upscope $end
$scope module ic1 $end
$var wire 1 % clk $end
$var wire 1 ( noisysignal $end
$var reg 1 / conditioned $end
$var reg 3 N counter [2:0] $end
$var reg 1 . negativeedge $end
$var reg 1 - positiveedge $end
$var reg 1 O synchronizer0 $end
$var reg 1 P synchronizer1 $end
$upscope $end
$scope module ic2 $end
$var wire 1 % clk $end
$var wire 1 $ noisysignal $end
$var reg 1 9 conditioned $end
$var reg 3 Q counter [2:0] $end
$var reg 1 8 negativeedge $end
$var reg 1 7 positiveedge $end
$var reg 1 R synchronizer0 $end
$var reg 1 S synchronizer1 $end
$upscope $end
$scope module miso_buff $end
$var wire 1 % clk $end
$var wire 1 + d $end
$var wire 1 . enable $end
$var reg 1 4 q $end
$upscope $end
$upscope $end
$scope module inWave $end
$var wire 16 T dataIn [15:0] $end
$var wire 1 & enable $end
$var wire 1 ( sclk $end
$var reg 1 $ actualCS $end
$var reg 1 # dataOut $end
$var reg 5 U pos [4:0] $end
$upscope $end
$upscope $end
$enddefinitions $end
#0
$dumpvars
b1111 U
b101011011110101 T
0S
0R
b0 Q
0P
0O
b0 N
0M
0L
b0 K
xJ
b101 I
xH
xG
b0 F
xE
bx D
bx C
bx B
bx A
bx @
bx ?
bx >
bx =
x<
bx ;
bx :
x9
x8
x7
bx 6
x5
x4
x3
x2
x1
x0
x/
x.
x-
bx ,
x+
x*
bz )
0(
x'
1&
0%
x$
0#
x"
bz !
$end
#10
xL
b1 K
b1 N
xR
b1 Q
1%
#20
0%
#30
xS
b10 Q
b10 N
xM
b10 K
1%
#40
0%
#50
b11 K
b11 N
b11 Q
1%
#60
0%
#70
b0 Q
0/
b0 N
b0 K
1%
#80
0%
#90
b1 K
0.
0-
b1 Q
1%
#100
0%
1(
#110
b10 Q
1O
b10 K
1%
#120
0%
#130
b11 K
1P
b11 Q
1%
#140
0%
#150
b0 Q
b1 N
b0 K
1%
#160
0%
#170
b1 K
b10 N
b1 Q
1%
#180
0%
#190
b10 Q
b11 N
b10 K
1%
#200
0&
1$
0%
0(
#210
b1 F
z"
03
0*
05
0<
b11 K
0O
1/
1-
b0 N
1R
b11 Q
1%
#220
0%
#230
1S
b0 Q
0P
0-
b0 K
bx ,
bx =
bx @
bx C
bx D
1%
#240
0%
#250
b1 K
b1 N
b1 Q
1%
#260
0%
#270
b10 Q
b10 N
b10 K
1%
#280
0%
#290
b11 K
b11 N
b11 Q
1%
#300
0%
1(
#310
19
b0 Q
1O
0/
1.
b0 N
b0 K
1%
#320
0%
#330
b1 K
1P
0.
08
07
1%
#340
0%
#350
b1 N
b10 K
1%
#360
0%
#370
b11 K
b10 N
1%
#380
0%
#390
b11 N
b0 K
1%
#400
0'
b1110 U
0$
0%
0(
#410
0J
b10 F
0L
b1 K
0O
1/
1-
b0 N
0R
1%
#420
0%
#430
0S
0P
0-
0M
b10 K
bx ,
bx =
bx @
bx C
bx D
1%
#440
0%
#450
b11 K
b1 N
b1 Q
1%
#460
0%
#470
b10 Q
b10 N
02
b0 K
1%
#480
0%
#490
01
00
b11 N
b11 Q
1%
#500
0%
1(
#510
09
18
b0 Q
1O
0/
1.
b0 N
1%
#520
0%
#530
1P
0.
08
1%
#540
0%
#550
b1 N
1%
#560
0%
#570
b10 N
1%
#580
0%
#590
b11 N
1%
#600
b1101 U
1#
0%
0(
#610
1J
b1 F
0O
1/
1-
b0 N
1%
#620
0%
#630
0P
0-
0E
bx0 ,
bx0 =
bx0 @
bx0 C
bx0 D
1%
#640
0%
#650
b1 N
1%
#660
0%
#670
b10 N
1%
#680
0%
#690
b11 N
1%
#700
1'
0%
1(
#710
1O
0/
1.
b0 N
1L
1%
#720
0%
#730
1M
1P
0.
1%
#740
0%
#750
b1 N
b1 K
1%
#760
0%
#770
b10 K
b10 N
1%
#780
0%
#790
b11 N
b11 K
1%
#800
b1100 U
0#
0%
0(
#810
b10 F
12
10
b0 K
0O
1/
1-
b0 N
1%
#820
0%
#830
0P
0-
00
1E
bx01 ,
bx01 =
bx01 @
bx01 C
bx01 D
1%
#840
0%
#850
b1 N
1%
#860
0%
#870
b10 N
1%
#880
0%
#890
b11 N
1%
#900
0'
0%
1(
#910
1O
0/
1.
b0 N
0L
1%
#920
0%
#930
0M
1P
0.
1%
#940
0%
#950
b1 N
b1 K
1%
#960
0%
#970
b10 K
b10 N
1%
#980
0%
#990
b11 N
b11 K
1%
#1000
b1011 U
1#
0%
0(
#1010
b11 F
02
11
b0 K
0O
1/
1-
b0 N
1%
#1020
0%
#1030
0P
0-
01
0E
bx010 ,
bx010 =
bx010 @
bx010 C
bx010 D
1%
#1040
0%
#1050
b1 N
1%
#1060
0%
#1070
b10 N
1%
#1080
0%
#1090
b11 N
1%
#1100
1'
0%
1(
#1110
1O
0/
1.
b0 N
1L
1%
#1120
0%
#1130
1M
1P
0.
1%
#1140
0%
#1150
b1 N
b1 K
1%
#1160
0%
#1170
b10 K
b10 N
1%
#1180
0%
#1190
b11 N
b11 K
1%
#1200
b1010 U
0#
0%
0(
#1210
b100 F
12
10
b0 K
0O
1/
1-
b0 N
1%
#1220
0%
#1230
0P
0-
00
1E
bx0101 ,
bx0101 =
bx0101 @
bx0101 C
bx0101 D
1%
#1240
0%
#1250
b1 N
1%
#1260
0%
#1270
b10 N
1%
#1280
0%
#1290
b11 N
1%
#1300
0'
0%
1(
#1310
1O
0/
1.
b0 N
0L
1%
#1320
0%
#1330
0M
1P
0.
1%
#1340
0%
#1350
b1 N
b1 K
1%
#1360
0%
#1370
b10 K
b10 N
1%
#1380
0%
#1390
b11 N
b11 K
1%
#1400
b1001 U
1#
0%
0(
#1410
b101 F
02
11
b0 K
0O
1/
1-
b0 N
1%
#1420
0%
#1430
0P
0-
01
0E
bx01010 ,
bx01010 =
bx01010 @
bx01010 C
bx01010 D
1%
#1440
0%
#1450
b1 N
1%
#1460
0%
#1470
b10 N
1%
#1480
0%
#1490
b11 N
1%
#1500
1'
0%
1(
#1510
1O
0/
1.
b0 N
1L
1%
#1520
0%
#1530
1M
1P
0.
1%
#1540
0%
#1550
b1 N
b1 K
1%
#1560
0%
#1570
b10 K
b10 N
1%
#1580
0%
#1590
b11 N
b11 K
1%
#1600
b1000 U
0%
0(
#1610
b110 F
12
10
b0 K
0O
1/
1-
b0 N
1%
#1620
0%
#1630
0P
0-
00
1E
bx010101 ,
bx010101 =
bx010101 @
bx010101 C
bx010101 D
1%
#1640
0%
#1650
b1 N
1%
#1660
0%
#1670
b10 N
1%
#1680
0%
#1690
b11 N
1%
#1700
0%
1(
#1710
1O
0/
1.
b0 N
1%
#1720
0%
#1730
1P
0.
1%
#1740
0%
#1750
b1 N
1%
#1760
0%
#1770
b10 N
1%
#1780
0%
#1790
b11 N
1%
#1800
b111 U
0#
0%
0(
#1810
b111 F
0O
1/
1-
b0 N
1%
#1820
0%
#1830
0P
0-
bx0101011 ,
bx0101011 =
bx0101011 @
bx0101011 C
bx0101011 D
1%
#1840
0%
#1850
b1 N
1%
#1860
0%
#1870
b10 N
1%
#1880
0%
#1890
b11 N
1%
#1900
0'
0%
1(
#1910
1O
0/
1.
b0 N
0L
1%
#1920
0%
#1930
0M
1P
0.
1%
#1940
0%
#1950
b1 N
b1 K
1%
#1960
0%
#1970
b10 K
b10 N
1%
#1980
0%
#1990
b11 N
b11 K
1%
#2000
b110 U
1#
0%
0(
#2010
1<
b0 F
b0 I
02
11
b0 K
0O
1/
1-
b0 N
1%
#2020
0%
#2030
b1010110 ;
b1010110 ?
b1010110 :
b1010110 >
0P
0-
01
0+
0E
b1010110 ,
b1010110 =
b1010110 @
b1010110 C
b1010110 D
1%
#2040
0%
#2050
b1 N
1%
#2060
0%
#2070
b10 N
1%
#2080
0%
#2090
b11 N
1%
#2100
1'
0%
1(
#2110
1O
0/
1.
b0 N
1L
1%
#2120
0%
#2130
1M
1P
0.
z"
04
1%
#2140
0%
#2150
b1 N
b1 K
1%
#2160
0%
#2170
b10 K
b10 N
1%
#2180
0%
#2190
b11 N
b11 K
1%
#2200
b101 U
0%
0(
#2210
b1 F
0H
b11 I
12
10
b0 K
0O
1/
1-
b0 N
1%
#2220
0%
#2230
b101101 ;
b101101 ?
b10101101 :
b10101101 >
0P
0-
00
1E
1+
b10101101 ,
b10101101 =
b10101101 @
b10101101 C
b10101101 D
1%
#2240
0%
#2250
b1 N
1%
#2260
0%
#2270
b10 N
1%
#2280
0%
#2290
b11 N
1%
#2300
0%
1(
#2310
1O
0/
1.
b0 N
1%
#2320
0%
#2330
1P
0.
z"
14
1%
#2340
0%
#2350
b1 N
1%
#2360
0%
#2370
b10 N
1%
#2380
0%
#2390
b11 N
1%
#2400
b100 U
0%
0(
#2410
0<
b10 F
1H
0O
1/
1-
b0 N
1%
#2420
0%
#2430
0P
0-
0+
b1011011 ,
b1011011 =
b1011011 @
b1011011 C
b1011011 D
1%
#2440
0%
#2450
b1 N
1%
#2460
0%
#2470
b10 N
1%
#2480
0%
#2490
b11 N
1%
#2500
0%
1(
#2510
1O
0/
1.
b0 N
1%
#2520
0%
#2530
1P
0.
z"
04
1%
#2540
0%
#2550
b1 N
1%
#2560
0%
#2570
b10 N
1%
#2580
0%
#2590
b11 N
1%
#2600
b11 U
0%
0(
#2610
b11 F
0O
1/
1-
b0 N
1%
#2620
0%
#2630
0P
0-
1+
b10110111 ,
b10110111 =
b10110111 @
b10110111 C
b10110111 D
1%
#2640
0%
#2650
b1 N
1%
#2660
0%
#2670
b10 N
1%
#2680
0%
#2690
b11 N
1%
#2700
0%
1(
#2710
1O
0/
1.
b0 N
1%
#2720
0%
#2730
1P
0.
z"
14
1%
#2740
0%
#2750
b1 N
1%
#2760
0%
#2770
b10 N
1%
#2780
0%
#2790
b11 N
1%
#2800
b10 U
0#
0%
0(
#2810
b100 F
0O
1/
1-
b0 N
1%
#2820
0%
#2830
0P
0-
0+
b1101111 ,
b1101111 =
b1101111 @
b1101111 C
b1101111 D
1%
#2840
0%
#2850
b1 N
1%
#2860
0%
#2870
b10 N
1%
#2880
0%
#2890
b11 N
1%
#2900
0'
0%
1(
#2910
1O
0/
1.
b0 N
0L
1%
#2920
0%
#2930
0M
1P
0.
z"
04
1%
#2940
0%
#2950
b1 N
b1 K
1%
#2960
0%
#2970
b10 K
b10 N
1%
#2980
0%
#2990
b11 N
b11 K
1%
#3000
b1 U
1#
0%
0(
#3010
b101 F
02
11
b0 K
0O
1/
1-
b0 N
1%
#3020
0%
#3030
0P
0-
01
1+
0E
b11011110 ,
b11011110 =
b11011110 @
b11011110 C
b11011110 D
1%
#3040
0%
#3050
b1 N
1%
#3060
0%
#3070
b10 N
1%
#3080
0%
#3090
b11 N
1%
#3100
1'
0%
1(
#3110
1O
0/
1.
b0 N
1L
1%
#3120
0%
#3130
1M
1P
0.
z"
14
1%
#3140
0%
#3150
b1 N
b1 K
1%
#3160
0%
#3170
b10 K
b10 N
1%
#3180
0%
#3190
b11 N
b11 K
1%
#3200
b1111 U
0#
0%
0(
#3210
b110 F
12
10
b0 K
0O
1/
1-
b0 N
1%
#3220
0%
#3230
0P
0-
00
1E
b10111101 ,
b10111101 =
b10111101 @
b10111101 C
b10111101 D
1%
#3240
0%
#3250
b1 N
1%
#3260
0%
#3270
b10 N
1%
#3280
0%
#3290
b11 N
1%
#3300
0'
0%
1(
#3310
1O
0/
1.
b0 N
0L
1%
#3320
0%
#3330
0M
1P
0.
1%
#3340
0%
#3350
b1 N
b1 K
1%
#3360
0%
#3370
b10 K
b10 N
1%
#3380
0%
#3390
b11 N
b11 K
1%
#3400
b1110 U
0%
0(
#3410
b111 F
b100 I
02
11
b0 K
0O
1/
1-
b0 N
1%
#3420
0%
#3430
0P
0-
01
0+
0E
b1111010 ,
b1111010 =
b1111010 @
b1111010 C
b1111010 D
1%
#3440
0%
#3450
b1 N
1%
#3460
0%
#3470
b10 N
1%
#3480
0%
#3490
b11 N
1%
#3500
0%
1(
#3510
1O
0/
1.
b0 N
1%
#3520
0%
#3530
1P
0.
z"
04
1%
#3540
0%
#3550
b1 N
1%
#3560
0%
#3570
b10 N
1%
#3580
0%
#3590
b11 N
1%
#3600
b1101 U
1#
0%
0(
#3610
15
b101 I
b0 F
0O
1/
1-
b0 N
1%
#3620
0%
#3630
0P
0-
1+
b11110100 ,
b11110100 =
b11110100 @
b11110100 C
b11110100 D
1%
#3640
0%
#3650
b1 N
b11110100 6
b11110100 A
b11110100 B
1%
#3660
0%
#3670
b10 N
1%
#3680
0%
#3690
b11 N
1%
#3700
1'
0%
1(
#3710
1O
0/
1.
b0 N
1L
1%
#3720
0%
#3730
1M
1P
0.
z"
14
1%
#3740
0%
#3750
b1 N
b1 K
1%
#3760
0%
#3770
b10 K
b10 N
1%
#3780
0%
#3790
b11 N
b11 K
1%
#3800
b1100 U
0#
0%
0(
#3810
b1 F
05
12
10
b0 K
0O
1/
1-
b0 N
1%
#3820
0%
#3830
0P
0-
00
1E
b11101001 ,
b11101001 =
b11101001 @
b11101001 C
b11101001 D
1%
#3840
0%
#3850
b1 N
1%
#3860
0%
#3870
b10 N
1%
#3880
0%
#3890
b11 N
1%
#3900
0'
0%
1(
#3910
1O
0/
1.
b0 N
0L
1%
#3920
0%
#3930
0M
1P
0.
1%
#3940
0%
#3950
b1 N
b1 K
1%
#3960
0%
#3970
b10 K
b10 N
1%
#3980
0%
#3990
b11 N
b11 K
1%
#4000
b1011 U
1#
0%
0(
#4010
b10 F
02
11
b0 K
0O
1/
1-
b0 N
1%
#4020
0%
#4030
0P
0-
01
0E
b11010010 ,
b11010010 =
b11010010 @
b11010010 C
b11010010 D
1%
#4040
0%
#4050
b1 N
1%
#4060
0%
#4070
b10 N
1%
#4080
0%
#4090
b11 N
1%
#4100
1'
0%
1(
#4110
1O
0/
1.
b0 N
1L
1%
#4120
0%
#4130
1M
1P
0.
1%
#4140
0%
#4150
b1 N
b1 K
1%
#4160
0%
#4170
b10 K
b10 N
1%
#4180
0%
#4190
b11 N
b11 K
1%
#4200
0#
0%
0(
