inputWave.v
module inputWave
(
  input[15:0] dataIn,
  input sclk,
  input enable,
  output reg dataOut
  );
  reg[4:0] pos;
  initial pos = 4'd15;
always @(negedge sclk)begin
  //pos = 15;
  dataOut = dataIn[pos];
  $display("On bit %b which equals %b", pos, dataIn[pos]);
  if (enable == 0)begin
    pos = pos - 1;
    end
  if (pos == 0000 && enable == 0)begin
    pos = 4'd15;
   end
end

endmodule

fsm.v
`define ADDRESS 3'd00
`define MISO_REG 3'd1
`define MISO_OUT 3'd2
`define MOSI_MEM 3'd3
`define MOSI_WRI 3'd4
`define OFF 3'd5
module fsm
(
  input  cs,
  input clk,
  input sclk,
  input  shiftRegOut0,
  output add_WE,
  output DM_WE,
  output SR_WE,
  output MISO_Buff
  );
      reg[2:0] state;
      initial state = `OFF;
      parameter waittime = 7;
      reg[4:0] counter;
      initial counter <= 0;
      reg miOut, moMem, turnOn;
      reg add_WE, DM_WE, SR_WE, MISO_Buff;

      always @(posedge sclk) begin
        if( counter == waittime) begin
            counter <= 0;
        end
        else begin
            counter <= counter+1;
        end
      end

      always @(posedge sclk) begin
      $display("Positive sclk edge");
      if (cs)begin
        state <= `OFF;
        turnOn <= 0;
        $display("In state OFF");
      end

      else if (cs == 0 && state==`OFF)begin
        if (turnOn == 0)begin
          counter = 0;
          turnOn = 1;
          $display("Turn on = %b",turnOn);
        end
        $display("In state OFF going to address");
        if (counter == 3'd7)begin
          state = `ADDRESS;
          $display("counter: %b",counter);
        end
        $display("counter: %b",counter);
      end

      else if (state == `ADDRESS && shiftRegOut0 == 1)begin
        state <= `MISO_REG;
        $display("In state ADDRESS going to miso_reg");
      end

      else if (state == `MISO_REG)begin
        state <= `MISO_OUT;
        miOut <= 0;
        $display("In state going to miso_out");
      end

      else if (state == `MISO_OUT)begin
        if (miOut == 0)begin
          counter <= 0;
          miOut <= 1;
          $display("In state of miso_out");
        end
        if (counter == 3'd7)
          state <= `OFF;
      end

      else if (state == `ADDRESS && shiftRegOut0 == 0)begin
        state <= `MOSI_MEM;
        moMem <= 0;
        $display("In state ADDRESS going to mosimem");
      end

      else if(state == `MOSI_MEM)begin
        $display("In state of mosimem");
        if (moMem == 0) begin
          moMem <= 1;
          counter <= 0;
          $display("MOSI counter: %b",counter);
        end
        if (counter == 3'd7)
          state <= `MOSI_WRI;
          $display("MOSI counter: %b",counter);
      end

      else if (state == `MOSI_WRI)begin
        $display("In state mosi_wri");
        state <= `OFF;
      end
      end

  always @(posedge sclk) begin
  case (state)
    `ADDRESS:   begin add_WE <= 1; DM_WE<=0; SR_WE <= 0; MISO_Buff <= 0; end
    `MISO_REG:  begin add_WE <= 0; DM_WE<=0; SR_WE <= 1; MISO_Buff <= 0; end
    `MOSI_MEM:  begin add_WE <= 0; DM_WE<=0; SR_WE <= 0; MISO_Buff <= 0; end
    `MISO_OUT:  begin add_WE <= 0; DM_WE<=0; SR_WE <= 0; MISO_Buff <= 1; end
    `MOSI_WRI:  begin add_WE <= 0; DM_WE<=1; SR_WE <= 0; MISO_Buff <= 0; end
    `OFF:       begin add_WE <= 0; DM_WE<=0; SR_WE <= 0; MISO_Buff <= 0; end
  endcase
  end

  endmodule

spimemory.v
//------------------------------------------------------------------------
// SPI Memory
//------------------------------------------------------------------------

`include "shiftregister.v"
`include "inputconditioner.v"
`include "datamemory.v"
`include "fsm.v"


module dff #( parameter W = 8)
(
    input clk,
    input enable,
    input      [W-1:0] d,
    output reg [W-1:0] q
);
    always @(posedge clk) begin
        if(enable) begin
            q <= d;
        end
    end
endmodule

module spiMemory
(
    input           clk,        // FPGA clock
    input           sclk_pin,   // SPI clock
    input           cs_pin,     // SPI chip select
    output          miso_pin,   // SPI master in slave out
    input           mosi_pin,   // SPI master out slave in
    output [3:0]    leds        // LEDs for debugging
);

	wire mosi_cond, mosi_pos, mosi_neg, sclk_cond, sclk_pos, sclk_neg, cs_cond, cs_pos, cs_neg;
    wire miso_bufe, dm_we, addr_we, sr_we;
    wire[7:0] shiftRegOutP, dataMemOut, addressLatchOut;
    wire[6:0] address;
    wire shiftRegOutS, misoPreBufe;

    assign address = addressLatchOut[6:0];

    inputconditioner ic0 (.clk(clk),
    					.noisysignal(mosi_pin),
    					.conditioned(mosi_cond),
    					.positiveedge(mosi_pos),
    					.negativeedge(mosi_neg));
    inputconditioner ic1 (.clk(clk),
    					.noisysignal(sclk_pin),
    					.conditioned(sclk_cond),
    					.positiveedge(sclk_pos),
    					.negativeedge(sclk_neg));
    inputconditioner ic2 (.clk(clk),
    					.noisysignal(cs_pin),
    					.conditioned(cs_cond),
    					.positiveedge(cs_pos),
    					.negativeedge(cs_neg));
	shiftregister #(8) dut(.clk(clk),
    		           .peripheralClkEdge(sclk_pos),
     		           .parallelLoad(sr_we),
     		           .parallelDataIn(dataMemOut),
     		           .serialDataIn(mosi_cond),
     		           .parallelDataOut(shiftRegOutP),
     		           .serialDataOut(shiftRegOutS));
	datamemory data_mem(.clk(clk),
    					.dataOut(dataMemOut),
    					.address(address),	// MSB OF INPUT BECOMES DM_WE
    					.writeEnable(dm_we),
   						.dataIn(shiftRegOutP));
	dff #(1) miso_buff (.clk(clk),
						.enable(sclk_neg),
						.d(shiftRegOutS),
						.q(misoPreBufe));
	dff #(8) addr_latch(.clk(clk),
						.enable(addr_we),
						.d(shiftRegOutP),
						.q(addressLatchOut));

	fsm finite_state_m (.cs(cs_cond),
						.clk(clk),
						.sclk(sclk_pos),
						.shiftRegOut0(shiftRegOutP[0]),
						.add_WE(addr_we),
						.DM_WE(dm_we),
						.SR_WE(sr_we),
						.MISO_Buff(miso_bufe));

	// bufif1(out, in, control)
	//           control
	// in |      0 1 x z
	// -----------------
	// 0  |      z 0 L L
	// 1  |      z 1 H H
	// x  |      z x x x
	// z  |      z x x x
	// L means that output has 0 or z value. H means that output has 1 or z value.
	// x represents an unknown logic value. z represents high impedance logic value.
	bufif1 miso_buffer(miso_pin, misoPreBufe, miso_bufe);

endmodule

datamemory.v
//------------------------------------------------------------------------
// Data Memory
//   Positive edge triggered
//   dataOut always has the value mem[address]
//   If writeEnable is true, writes dataIn to mem[address]
//------------------------------------------------------------------------

module datamemory
#(
    parameter addresswidth  = 7,
    parameter depth         = 2**addresswidth,
    parameter width         = 8
)
(
    input 		                clk,
    output reg [width-1:0]      dataOut,
    input [addresswidth-1:0]    address,
    input                       writeEnable,
    input [width-1:0]           dataIn
);


    reg [width-1:0] memory [depth-1:0];

    always @(posedge clk) begin
        if(writeEnable)begin
            $display("Write Enable: %b",writeEnable);
            memory[address] <= dataIn;
            end
        dataOut <= memory[address];
    end

endmodule

shiftregister.v
//------------------------------------------------------------------------
// Shift Register
//   Parameterized width (in bits)
//   Shift register can operate in two modes:
//      - serial in, parallel out
//      - parallel in, serial out
//------------------------------------------------------------------------

module shiftregister
#(parameter width = 8)
(
input               clk,                // FPGA Clock
input               peripheralClkEdge,  // Edge indicator
input               parallelLoad,       // 1 = Load shift reg with parallelDataIn
input  [width-1:0]  parallelDataIn,     // Load shift reg in parallel
input               serialDataIn,       // Load shift reg serially
output [width-1:0]  parallelDataOut,    // Shift reg data contents
output              serialDataOut       // Positive edge synchronized
);

    reg [width-1:0]      shiftregistermem;
    assign serialDataOut = shiftregistermem[width-1];
    assign parallelDataOut = shiftregistermem;
    always @(posedge clk) begin
      if (parallelLoad ==1) begin
        shiftregistermem <= parallelDataIn;
      end
      else if (peripheralClkEdge == 1) begin
        shiftregistermem <= shiftregistermem<<1;
        $display("Shift Register address: %b",shiftregistermem);
        shiftregistermem[0] <= serialDataIn;
      end
    end

endmodule

inputconditioner.v
//------------------------------------------------------------------------
// Input Conditioner
//    1) Synchronizes input to clock domain
//    2) Debounces input
//    3) Creates pulses at edge transitions
//------------------------------------------------------------------------

module inputconditioner
(
input 	    clk,            // Clock domain to synchronize input to
input	    noisysignal,    // (Potentially) noisy input signal
output reg  conditioned,    // Conditioned output signal
output reg  positiveedge,   // 1 clk pulse at rising edge of conditioned
output reg  negativeedge    // 1 clk pulse at falling edge of conditioned
);

    parameter counterwidth = 3; // Counter size, in bits, >= log2(waittime)
    parameter waittime = 3;     // Debounce delay, in clock cycles
    
    reg[counterwidth-1:0] counter = 0;
    reg synchronizer0 = 0;
    reg synchronizer1 = 0;

    always @(posedge clk ) begin
        
        if(conditioned == synchronizer1) begin
            counter <= 0;
            // Reset edge detect
            positiveedge <= 0;
            negativeedge <= 0;
        end
        else begin
            if( counter == waittime) begin
                counter <= 0;
                // Signal about to go through d flip flop. Now is the time to look at 
                if (synchronizer1 == 1 && conditioned == 0)
                    positiveedge <= 1;
                if (synchronizer1 == 0 && conditioned == 1)
                    negativeedge <= 1;
                conditioned <= synchronizer1;
            end
            else 
                counter <= counter+1;
        end

        synchronizer0 <= noisysignal;
        synchronizer1 <= synchronizer0;

    end

endmodule

spimemory.t.v

`include "spimemory.v"
`include "inputWave.v"



module spimemory_test();

	reg clk, sclk_pin, cs_pin, mosi_pin;
	wire dataOut;
	always #10 clk = !clk;
	always #100 sclk_pin = !sclk_pin;
	wire miso_pin;
	wire[3:0] leds;
	parameter write_op = 16'b0101011011110101;
	parameter read_op = 8'b01010111;
	parameter ad_test = 6'b000000;


	spiMemory dut(.clk(clk), .sclk_pin(sclk_pin), .cs_pin(cs_pin), .miso_pin(miso_pin), .mosi_pin(mosi_pin), .leds(leds));
	inputWave inWave(.dataIn(write_op),.sclk(sclk_pin),.enable(cs_pin),.dataOut(dataOut));



	initial sclk_pin = 0;
	initial clk = 0;


	initial begin
	mosi_pin <= dataOut;
    $dumpfile("spi.vcd"); //Creating .vcd file for timing analysis
    $dumpvars;
	cs_pin <= 1;#100
	$display("STARTING NOW!");
	cs_pin <= 0;#200
	mosi_pin <= dataOut;
	//mosi_pin = write_op[0]; #100
	$display(dut.addr_we);
	$display(dut.data_mem.address);#200
	mosi_pin <= dataOut;
	//mosi_pin = write_op[1]; #100
	//mosi_pin = write_op[2]; #100
	//mosi_pin = write_op[3]; #100
	$display(dut.addr_we);
	$display(dut.data_mem.address);#200
	mosi_pin <= dataOut;
	//mosi_pin = write_op[4]; #100
	//mosi_pin = write_op[5]; #100
	$display(dut.addr_we);
	$display(dut.data_mem.address);#200
	mosi_pin <= dataOut;
	//mosi_pin = write_op[6]; #100
	//mosi_pin = write_op[7]; #100
	$display(dut.addr_we);
	$display(dut.data_mem.address);#200
	mosi_pin <= dataOut;
	//mosi_pin = write_op[8]; #100
	$display("Address: %b",dut.addr_we);
	$display("DatMem: %b",dut.dm_we);#200
	mosi_pin <= dataOut;
	//mosi_pin = write_op[9]; #100
	$display("DatMem: %b",dut.dm_we);
	$display("ADDRESS: %b",dut.data_mem.address);#200
	mosi_pin <= dataOut;
	//mosi_pin = write_op[10]; #100
	$display("DatMem: %b",dut.dm_we);
	$display("ADDRESS: %b",dut.data_mem.address);#200
	mosi_pin <= dataOut;
	//mosi_pin = write_op[11]; #100
	$display("DatMem: %b",dut.dm_we);
	$display("ADDRESS: %b",dut.data_mem.address);#200
	mosi_pin <= dataOut;
	$display("DatMem: %b",dut.dm_we);
	$display("ADDRESS: %b",dut.data_mem.address);#200
	//mosi_pin = write_op[13]; #100
	mosi_pin <= dataOut;
	$display("DatMem: %b",dut.dm_we);
	$display("ADDRESS: %b",dut.data_mem.address);#200
	//mosi_pin = write_op[14]; #100
	mosi_pin <= dataOut;
	$display("DatMem: %b",dut.dm_we);
	$display("ADDRESS: %b",dut.data_mem.address);#200
	//mosi_pin = write_op[15]; #100
	mosi_pin <= dataOut;
	$display("DatMem: %b",dut.dm_we);
	$display("ADDRESS: %b",dut.data_mem.address);
	#200 $display("DatMem: %b",dut.dm_we);
	#200 $display("DatMem: %b",dut.dm_we);
	#200 $display("DatMem: %b",dut.dm_we);
	#200 $display("DatMem: %b",dut.dm_we);
	$display("Address: %b",dut.data_mem.address);
	//#10000;
	$finish;

	end

endmodule

spi.vcd
$date
	Tue Oct 23 17:16:08 2018
$end
$version
	Icarus Verilog
$end
$timescale
	1s
$end
$scope module spimemory_test $end
$var wire 4 ! leds [3:0] $end
$var wire 1 " miso_pin $end
$var wire 1 # dataOut $end
$var reg 1 $ clk $end
$var reg 1 % cs_pin $end
$var reg 1 & mosi_pin $end
$var reg 1 ' sclk_pin $end
$scope module dut $end
$var wire 1 $ clk $end
$var wire 1 % cs_pin $end
$var wire 4 ( leds [3:0] $end
$var wire 1 " miso_pin $end
$var wire 1 & mosi_pin $end
$var wire 1 ' sclk_pin $end
$var wire 1 ) sr_we $end
$var wire 1 * shiftRegOutS $end
$var wire 8 + shiftRegOutP [7:0] $end
$var wire 1 , sclk_pos $end
$var wire 1 - sclk_neg $end
$var wire 1 . sclk_cond $end
$var wire 1 / mosi_pos $end
$var wire 1 0 mosi_neg $end
$var wire 1 1 mosi_cond $end
$var wire 1 2 miso_bufe $end
$var wire 1 3 misoPreBufe $end
$var wire 1 4 dm_we $end
$var wire 8 5 dataMemOut [7:0] $end
$var wire 1 6 cs_pos $end
$var wire 1 7 cs_neg $end
$var wire 1 8 cs_cond $end
$var wire 8 9 addressLatchOut [7:0] $end
$var wire 7 : address [6:0] $end
$var wire 1 ; addr_we $end
$scope module addr_latch $end
$var wire 1 $ clk $end
$var wire 1 ; enable $end
$var wire 8 < d [7:0] $end
$var reg 8 = q [7:0] $end
$upscope $end
$scope module data_mem $end
$var wire 7 > address [6:0] $end
$var wire 1 $ clk $end
$var wire 1 4 writeEnable $end
$var wire 8 ? dataIn [7:0] $end
$var reg 8 @ dataOut [7:0] $end
$upscope $end
$scope module dut $end
$var wire 1 $ clk $end
$var wire 8 A parallelDataIn [7:0] $end
$var wire 8 B parallelDataOut [7:0] $end
$var wire 1 * serialDataOut $end
$var wire 1 1 serialDataIn $end
$var wire 1 , peripheralClkEdge $end
$var wire 1 ) parallelLoad $end
$var reg 8 C shiftregistermem [7:0] $end
$upscope $end
$scope module finite_state_m $end
$var wire 1 $ clk $end
$var wire 1 D shiftRegOut0 $end
$var wire 1 , sclk $end
$var wire 1 8 cs $end
$var reg 1 4 DM_WE $end
$var reg 1 2 MISO_Buff $end
$var reg 1 ) SR_WE $end
$var reg 1 ; add_WE $end
$var reg 5 E counter [4:0] $end
$var reg 1 F miOut $end
$var reg 1 G moMem $end
$var reg 3 H state [2:0] $end
$var reg 1 I turnOn $end
$upscope $end
$scope module ic0 $end
$var wire 1 $ clk $end
$var wire 1 & noisysignal $end
$var reg 1 1 conditioned $end
$var reg 3 J counter [2:0] $end
$var reg 1 0 negativeedge $end
$var reg 1 / positiveedge $end
$var reg 1 K synchronizer0 $end
$var reg 1 L synchronizer1 $end
$upscope $end
$scope module ic1 $end
$var wire 1 $ clk $end
$var wire 1 ' noisysignal $end
$var reg 1 . conditioned $end
$var reg 3 M counter [2:0] $end
$var reg 1 - negativeedge $end
$var reg 1 , positiveedge $end
$var reg 1 N synchronizer0 $end
$var reg 1 O synchronizer1 $end
$upscope $end
$scope module ic2 $end
$var wire 1 $ clk $end
$var wire 1 % noisysignal $end
$var reg 1 8 conditioned $end
$var reg 3 P counter [2:0] $end
$var reg 1 7 negativeedge $end
$var reg 1 6 positiveedge $end
$var reg 1 Q synchronizer0 $end
$var reg 1 R synchronizer1 $end
$upscope $end
$scope module miso_buff $end
$var wire 1 $ clk $end
$var wire 1 * d $end
$var wire 1 - enable $end
$var reg 1 3 q $end
$upscope $end
$upscope $end
$scope module inWave $end
$var wire 16 S dataIn [15:0] $end
$var wire 1 % enable $end
$var wire 1 ' sclk $end
$var reg 1 # dataOut $end
$var reg 5 T pos [4:0] $end
$upscope $end
$upscope $end
$enddefinitions $end
#0
$dumpvars
b1111 T
b101011011110101 S
0R
0Q
b0 P
0O
0N
b0 M
0L
0K
b0 J
xI
b101 H
xG
xF
b0 E
xD
bx C
bx B
bx A
bx @
bx ?
bx >
bx =
bx <
x;
bx :
bx 9
x8
x7
x6
bx 5
x4
x3
x2
x1
x0
x/
x.
x-
x,
bx +
x*
x)
bz (
0'
x&
1%
0$
0#
x"
bz !
$end
#10
xK
b1 J
b1 M
1Q
b1 P
1$
#20
0$
#30
1R
b10 P
b10 M
xL
b10 J
1$
#40
0$
#50
b11 J
b11 M
b11 P
1$
#60
0$
#70
18
b0 P
0.
b0 M
b0 J
1$
#80
0$
#90
b1 J
0-
0,
07
06
1$
#100
0%
0$
1'
#110
0Q
1N
b10 J
1$
#120
0$
#130
b11 J
1O
0R
1$
#140
0$
#150
b1 P
b1 M
b0 J
1$
#160
0$
#170
b1 J
b10 M
b10 P
1$
#180
0$
#190
b11 P
b11 M
b10 J
1$
#200
b1110 T
0$
0'
#210
b1 E
z"
02
0)
04
0;
b11 J
0N
1.
1,
b0 M
08
17
b0 P
1$
#220
0$
#230
bx +
bx <
bx ?
bx B
bx C
07
0O
0,
b0 J
1$
#240
0$
#250
b1 J
b1 M
1$
#260
0$
#270
b10 M
b10 J
1$
#280
0$
#290
b11 J
b11 M
1$
#300
0&
0$
1'
#310
1N
0.
1-
b0 M
0K
b0 J
1$
#320
0$
#330
0L
b1 J
1O
0-
1$
#340
0$
#350
b1 M
b10 J
1$
#360
0$
#370
b11 J
b10 M
1$
#380
0$
#390
b11 M
01
b0 J
1$
#400
b1101 T
1#
0$
0'
#410
b10 E
00
0/
0N
1.
1,
b0 M
1$
#420
0$
#430
0D
bx0 +
bx0 <
bx0 ?
bx0 B
bx0 C
0O
0,
1$
#440
0$
#450
b1 M
1$
#460
0$
#470
b10 M
1$
#480
0$
#490
b11 M
1$
#500
1&
0$
1'
#510
1N
0.
1-
b0 M
1K
1$
#520
0$
#530
1L
1O
0-
1$
#540
0$
#550
b1 M
b1 J
1$
#560
0$
#570
b10 J
b10 M
1$
#580
0$
#590
b11 M
b11 J
1$
#600
b1100 T
0#
0$
0'
#610
b11 E
11
1/
b0 J
0N
1.
1,
b0 M
1$
#620
0$
#630
1D
bx01 +
bx01 <
bx01 ?
bx01 B
bx01 C
0O
0,
0/
1$
#640
0$
#650
b1 M
1$
#660
0$
#670
b10 M
1$
#680
0$
#690
b11 M
1$
#700
0&
0$
1'
#710
1N
0.
1-
b0 M
0K
1$
#720
0$
#730
0L
1O
0-
1$
#740
0$
#750
b1 M
b1 J
1$
#760
0$
#770
b10 J
b10 M
1$
#780
0$
#790
b11 M
b11 J
1$
#800
b1011 T
1#
0$
0'
#810
b100 E
01
10
b0 J
0N
1.
1,
b0 M
1$
#820
0$
#830
0D
bx010 +
bx010 <
bx010 ?
bx010 B
bx010 C
0O
0,
00
1$
#840
0$
#850
b1 M
1$
#860
0$
#870
b10 M
1$
#880
0$
#890
b11 M
1$
#900
1&
0$
1'
#910
1N
0.
1-
b0 M
1K
1$
#920
0$
#930
1L
1O
0-
1$
#940
0$
#950
b1 M
b1 J
1$
#960
0$
#970
b10 J
b10 M
1$
#980
0$
#990
b11 M
b11 J
1$
#1000
b1010 T
0#
0$
0'
#1010
b101 E
11
1/
b0 J
0N
1.
1,
b0 M
1$
#1020
0$
#1030
1D
bx0101 +
bx0101 <
bx0101 ?
bx0101 B
bx0101 C
0O
0,
0/
1$
#1040
0$
#1050
b1 M
1$
#1060
0$
#1070
b10 M
1$
#1080
0$
#1090
b11 M
1$
#1100
0&
0$
1'
#1110
1N
0.
1-
b0 M
0K
1$
#1120
0$
#1130
0L
1O
0-
1$
#1140
0$
#1150
b1 M
b1 J
1$
#1160
0$
#1170
b10 J
b10 M
1$
#1180
0$
#1190
b11 M
b11 J
1$
#1200
b1001 T
1#
0$
0'
#1210
b110 E
01
10
b0 J
0N
1.
1,
b0 M
1$
#1220
0$
#1230
0D
bx01010 +
bx01010 <
bx01010 ?
bx01010 B
bx01010 C
0O
0,
00
1$
#1240
0$
#1250
b1 M
1$
#1260
0$
#1270
b10 M
1$
#1280
0$
#1290
b11 M
1$
#1300
1&
0$
1'
#1310
1N
0.
1-
b0 M
1K
1$
#1320
0$
#1330
1L
1O
0-
1$
#1340
0$
#1350
b1 M
b1 J
1$
#1360
0$
#1370
b10 J
b10 M
1$
#1380
0$
#1390
b11 M
b11 J
1$
#1400
b1000 T
0$
0'
#1410
b111 E
11
1/
b0 J
0N
1.
1,
b0 M
1$
#1420
0$
#1430
1D
bx010101 +
bx010101 <
bx010101 ?
bx010101 B
bx010101 C
0O
0,
0/
1$
#1440
0$
#1450
b1 M
1$
#1460
0$
#1470
b10 M
1$
#1480
0$
#1490
b11 M
1$
#1500
0$
1'
#1510
1N
0.
1-
b0 M
1$
#1520
0$
#1530
1O
0-
1$
#1540
0$
#1550
b1 M
1$
#1560
0$
#1570
b10 M
1$
#1580
0$
#1590
b11 M
1$
#1600
b111 T
0#
0$
0'
#1610
1;
b0 E
b0 H
0N
1.
1,
b0 M
1$
#1620
0$
#1630
bx010101 :
bx010101 >
bx010101 9
bx010101 =
bx0101011 +
bx0101011 <
bx0101011 ?
bx0101011 B
bx0101011 C
0O
0,
1$
#1640
0$
#1650
b101011 :
b101011 >
b1 M
bx0101011 9
bx0101011 =
1$
#1660
0$
#1670
b10 M
1$
#1680
0$
#1690
b11 M
1$
#1700
0&
0$
1'
#1710
1N
0.
1-
b0 M
0K
1$
#1720
0$
#1730
0L
1O
0-
1$
#1740
0$
#1750
b1 M
b1 J
1$
#1760
0$
#1770
b10 J
b10 M
1$
#1780
0$
#1790
b11 M
b11 J
1$
#1800
b110 T
1#
0$
0'
#1810
b1 E
b1 H
01
10
b0 J
0N
1.
1,
b0 M
1$
#1820
0$
#1830
0*
0D
b1010110 +
b1010110 <
b1010110 ?
b1010110 B
b1010110 C
0O
0,
00
1$
#1840
0$
#1850
b1010110 :
b1010110 >
b1 M
b1010110 9
b1010110 =
1$
#1860
0$
#1870
b10 M
1$
#1880
0$
#1890
b11 M
1$
#1900
1&
0$
1'
#1910
1N
0.
1-
b0 M
1K
1$
#1920
0$
#1930
1L
1O
0-
z"
03
1$
#1940
0$
#1950
b1 M
b1 J
1$
#1960
0$
#1970
b10 J
b10 M
1$
#1980
0$
#1990
b11 M
b11 J
1$
#2000
b101 T
0$
0'
#2010
1)
0;
0F
b10 H
b10 E
11
1/
b0 J
0N
1.
1,
b0 M
1$
#2020
0$
#2030
x*
xD
bx +
bx <
bx ?
bx B
bx C
0O
0,
0/
1$
#2040
0$
#2050
b1 M
1$
#2060
0$
#2070
b10 M
1$
#2080
0$
#2090
b11 M
1$
#2100
0$
1'
#2110
1N
0.
1-
b0 M
1$
#2120
0$
#2130
1O
0-
z"
x3
1$
#2140
0$
#2150
b1 M
1$
#2160
0$
#2170
b10 M
1$
#2180
0$
#2190
b11 M
1$
#2200
b100 T
0$
0'
#2210
1F
b11 E
x"
12
0)
0N
1.
1,
b0 M
1$
#2220
0$
#2230
1D
bx1 +
bx1 <
bx1 ?
bx1 B
bx1 C
0O
0,
1$
#2240
0$
#2250
b1 M
1$
#2260
0$
#2270
b10 M
1$
#2280
0$
#2290
b11 M
1$
#2300
0$
1'
#2310
1N
0.
1-
b0 M
1$
#2320
0$
#2330
1O
0-
1$
#2340
0$
#2350
b1 M
1$
#2360
0$
#2370
b10 M
1$
#2380
0$
#2390
b11 M
1$
#2400
b11 T
0$
0'
#2410
b100 E
0N
1.
1,
b0 M
1$
#2420
0$
#2430
bx11 +
bx11 <
bx11 ?
bx11 B
bx11 C
0O
0,
1$
#2440
0$
#2450
b1 M
1$
#2460
0$
#2470
b10 M
1$
#2480
0$
#2490
b11 M
1$
#2500
0$
1'
#2510
1N
0.
1-
b0 M
1$
#2520
0$
#2530
1O
0-
1$
#2540
0$
#2550
b1 M
1$
#2560
0$
#2570
b10 M
1$
#2580
0$
#2590
b11 M
1$
#2600
b10 T
0#
0$
0'
#2610
b101 E
0N
1.
1,
b0 M
1$
#2620
0$
#2630
bx111 +
bx111 <
bx111 ?
bx111 B
bx111 C
0O
0,
1$
#2640
0$
#2650
b1 M
1$
#2660
0$
#2670
b10 M
1$
#2680
0$
#2690
b11 M
1$
#2700
0$
1'
#2710
1N
0.
1-
b0 M
1$
#2720
0$
#2730
1O
0-
1$
#2740
0$
#2750
b1 M
1$
#2760
0$
#2770
b10 M
1$
#2780
0$
#2790
b11 M
1$
#2800
b1 T
1#
0$
0'
#2810
b110 E
0N
1.
1,
b0 M
1$
#2820
0$
#2830
bx1111 +
bx1111 <
bx1111 ?
bx1111 B
bx1111 C
0O
0,
1$
#2840
0$
#2850
b1 M
1$
#2860
0$
#2870
b10 M
1$
#2880
0$
#2890
b11 M
1$
#2900
0$
1'
#2910
1N
0.
1-
b0 M
1$
#2920
0$
#2930
1O
0-
1$
#2940
0$
#2950
b1 M
1$
#2960
0$
#2970
b10 M
1$
#2980
0$
#2990
b11 M
1$
#3000
b1111 T
0#
0$
0'
#3010
b111 E
0N
1.
1,
b0 M
1$
#3020
0$
#3030
bx11111 +
bx11111 <
bx11111 ?
bx11111 B
bx11111 C
0O
0,
1$
#3040
0$
#3050
b1 M
1$
#3060
0$
#3070
b10 M
1$
#3080
0$
#3090
b11 M
1$
#3100
0$
1'
#3110
1N
0.
1-
b0 M
1$
#3120
0$
#3130
1O
0-
1$
#3140
0$
#3150
b1 M
1$
#3160
0$
#3170
b10 M
1$
#3180
0$
#3190
b11 M
1$
#3200
b1110 T
0$
0'
#3210
b101 H
b0 E
0N
1.
1,
b0 M
1$
#3220
0$
#3230
bx111111 +
bx111111 <
bx111111 ?
bx111111 B
bx111111 C
0O
0,
1$
#3240
0$
#3250
b1 M
1$
#3260
0$
#3270
b10 M
1$
#3280
0$
#3290
b11 M
1$
