fsm.v
`define ADDRESS 3'd00
`define MISO_REG 3'd1
`define MISO_OUT 3'd2
`define MOSI_MEM 3'd3
`define MOSI_WRI 3'd4
`define PreADDRESS 3'd6
`define OFF 3'd5
module fsm
(
  input cs,
  input sclk,
  input  shiftRegOut0,
  output add_WE,
  output DM_WE,
  output SR_WE,
  output MISO_Buff, 
  output[4:0] counter
  );
      reg[2:0] state;

      initial state = `OFF;

      reg[4:0] counter;

      reg add_WE, DM_WE, SR_WE, MISO_Buff;

      always @(posedge sclk) begin


      //case (state)
       // `ADDRESS:   begin add_WE <= 1; DM_WE<=0; SR_WE <= 0; MISO_Buff <= 0; end
      // `MISO_REG:  begin add_WE <= 0; DM_WE<=0; SR_WE <= 1; MISO_Buff <= 0; end
      //   `MOSI_MEM:  begin add_WE <= 0; DM_WE<=0; SR_WE <= 0; MISO_Buff <= 0; end
      //   `MISO_OUT:  begin add_WE <= 0; DM_WE<=0; SR_WE <= 0; MISO_Buff <= 1; end
      //   `MOSI_WRI:  begin add_WE <= 0; DM_WE<=1; SR_WE <= 0; MISO_Buff <= 0; end
      //   `OFF:       begin add_WE <= 0; DM_WE<=0; SR_WE <= 0; MISO_Buff <= 0; end
      // endcase


      $display("Counter %d, State %d, add %b, dm %b, sr %b, buff %b, cs %b, shiftRegOut0, %b", counter, state, add_WE, DM_WE, SR_WE, MISO_Buff, cs, shiftRegOut0);
      counter <= counter+1;

      if (cs) begin
        state <= `OFF;
        counter <= 0;
      end

      else if (cs == 0 && state == `OFF) begin
        counter <= counter+1;
        if (counter == 6) begin  // Wait for 7 bits to clock in. Takes an extra clock for everything to push through the FSM
          state <= `PreADDRESS;
        end
      end
      else if (state == `PreADDRESS)begin
        state <= `ADDRESS;
      end
      else if (state == `ADDRESS && shiftRegOut0 == 1) begin
        state <= `MISO_REG;
      end

      else if (state == `MISO_REG)begin
        state <= `MISO_OUT;
        counter <= 0;
      end

      else if (state == `MISO_OUT)begin
        if (counter == 7 + 1) begin  // Wait for 8 bits to clock out. Takes an extra clock for everything to push through the FSM
          state <= `OFF;
          end
      end

      else if (state == `ADDRESS && shiftRegOut0 == 0) begin
        state <= `MOSI_MEM;
        counter <= 0;
      end

      else if(state == `MOSI_MEM) begin
        if (counter == 6) begin // Wait for 8 bits to clock in (immediately on the 8th, change memory). Takes an extra clock for everything to push through the FSM
          state <= `MOSI_WRI;
          end
      end

      else if (state == `MOSI_WRI)begin
        state <= `OFF;
      end

  end


    always @ (state) begin
          case (state)
        `PreADDRESS: begin add_WE <=1; DM_WE<=0; SR_WE <= 0; MISO_Buff <= 0; end
        `ADDRESS:   begin add_WE <= 0; DM_WE<=0; SR_WE <= 0; MISO_Buff <= 0; end
        `MISO_REG:  begin add_WE <= 0; DM_WE<=0; SR_WE <= 1; MISO_Buff <= 0; end
        `MOSI_MEM:  begin add_WE <= 0; DM_WE<=0; SR_WE <= 0; MISO_Buff <= 0; end
        `MISO_OUT:  begin add_WE <= 0; DM_WE<=0; SR_WE <= 0; MISO_Buff <= 1; end
        `MOSI_WRI:  begin add_WE <= 0; DM_WE<=1; SR_WE <= 0; MISO_Buff <= 0; end
        `OFF:       begin add_WE <= 0; DM_WE<=0; SR_WE <= 0; MISO_Buff <= 0; end
      endcase
      end


  endmodule

spimemory.v
//------------------------------------------------------------------------
// SPI Memory
//------------------------------------------------------------------------

`include "shiftregister.v"
`include "inputconditioner.v"
`include "datamemory.v"
`include "fsm.v"


module dff #( parameter W = 8)
(
    input clk,
    input enable,
    input      [W-1:0] d,
    output reg [W-1:0] q
);
    always @(posedge clk) begin
        if(enable) begin
            q <= d;
        end
    end
endmodule

module spiMemory
(
    input           clk,        // FPGA clock
    input           sclk_pin,   // SPI clock
    input           cs_pin,     // SPI chip select
    output          miso_pin,   // SPI master in slave out
    input           mosi_pin,   // SPI master out slave in
    output [3:0]    leds        // LEDs for debugging
);

	wire mosi_cond, mosi_pos, mosi_neg, sclk_cond, sclk_pos, sclk_neg, cs_cond, cs_pos, cs_neg;
    wire miso_bufe, dm_we, addr_we, sr_we;
    wire[7:0] shiftRegOutP, dataMemOut, addressLatchOut;
    wire[6:0] address;
    wire shiftRegOutS, misoPreBufe;
    wire[4:0] counter;

    assign address = addressLatchOut[6:0];

    inputconditioner ic0 (.clk(clk),
    					.noisysignal(mosi_pin),
    					.conditioned(mosi_cond),
    					.positiveedge(mosi_pos),
    					.negativeedge(mosi_neg));

    inputconditioner ic1 (.clk(clk),
    					.noisysignal(sclk_pin),
    					.conditioned(sclk_cond),
    					.positiveedge(sclk_pos),
    					.negativeedge(sclk_neg));

    inputconditioner ic2 (.clk(clk),
    					.noisysignal(cs_pin),
    					.conditioned(cs_cond),
    					.positiveedge(cs_pos),
    					.negativeedge(cs_neg));

	shiftregister #(8) sr(.clk(sclk_cond),
    		           .peripheralClkEdge(sclk_pos),
     		           .parallelLoad(sr_we),
     		           .parallelDataIn(dataMemOut),
     		           .serialDataIn(mosi_cond),
     		           .parallelDataOut(shiftRegOutP),
     		           .serialDataOut(shiftRegOutS));

	datamemory data_mem(.clk(clk),
    					.dataOut(dataMemOut),
    					.address(address),	// MSB OF INPUT BECOMES DM_WE
    					.writeEnable(dm_we),
   						.dataIn(shiftRegOutP));

	dff #(1) miso_buff (.clk(clk),
						.enable(sclk_neg),
						.d(shiftRegOutS),
						.q(misoPreBufe));
    
	dff #(8) addr_latch(.clk(clk),
						.enable(addr_we),
						.d(shiftRegOutP),
						.q(addressLatchOut));

	fsm finite_state_m (.cs(cs_cond),
						.sclk(sclk_cond),
						.shiftRegOut0(shiftRegOutP[0]),
                        .counter(counter),
						.add_WE(addr_we),
						.DM_WE(dm_we),
						.SR_WE(sr_we),
						.MISO_Buff(miso_bufe));

	// bufif1(out, in, control)
	//           control
	// in |      0 1 x z
	// -----------------
	// 0  |      z 0 L L
	// 1  |      z 1 H H
	// x  |      z x x x
	// z  |      z x x x
	// L means that output has 0 or z value. H means that output has 1 or z value.
	// x represents an unknown logic value. z represents high impedance logic value.
	bufif1 miso_buffer(miso_pin, misoPreBufe, miso_bufe);

endmodule

datamemory.v
//------------------------------------------------------------------------
// Data Memory
//   Positive edge triggered
//   dataOut always has the value mem[address]
//   If writeEnable is true, writes dataIn to mem[address]
//------------------------------------------------------------------------

module datamemory
#(
    parameter addresswidth  = 7,
    parameter depth         = 2**addresswidth,
    parameter width         = 8
)
(
    input 		                clk,
    output reg [width-1:0]      dataOut,
    input [addresswidth-1:0]    address,
    input                       writeEnable,
    input [width-1:0]           dataIn
);


    reg [width-1:0] memory [depth-1:0];

    always @(posedge clk) begin
        if(writeEnable)begin
            memory[address] <= dataIn;
            end
        dataOut <= memory[address];
    end

endmodule

shiftregister.v
//------------------------------------------------------------------------
// Shift Register
//   Parameterized width (in bits)
//   Shift register can operate in two modes:
//      - serial in, parallel out
//      - parallel in, serial out
//------------------------------------------------------------------------

module shiftregister
#(parameter width = 8)
(
input               clk,                // FPGA Clock
input               peripheralClkEdge,  // Edge indicator
input               parallelLoad,       // 1 = Load shift reg with parallelDataIn
input  [width-1:0]  parallelDataIn,     // Load shift reg in parallel
input               serialDataIn,       // Load shift reg serially
output [width-1:0]  parallelDataOut,    // Shift reg data contents
output              serialDataOut       // Positive edge synchronized
);

    reg [width-1:0]      shiftregistermem;
    assign serialDataOut = shiftregistermem[width-1];
    assign parallelDataOut = shiftregistermem;
    always @(posedge clk) begin
      if (parallelLoad ==1) begin
        shiftregistermem <= parallelDataIn;
      end
      else if (peripheralClkEdge == 1) begin
        shiftregistermem = shiftregistermem<<1;
        shiftregistermem[0] = serialDataIn;
      end
    end

endmodule

inputconditioner.v
//------------------------------------------------------------------------
// Input Conditioner
//    1) Synchronizes input to clock domain
//    2) Debounces input
//    3) Creates pulses at edge transitions
//------------------------------------------------------------------------

module inputconditioner
(
input 	    clk,            // Clock domain to synchronize input to
input	    noisysignal,    // (Potentially) noisy input signal
output reg  conditioned,    // Conditioned output signal
output reg  positiveedge,   // 1 clk pulse at rising edge of conditioned
output reg  negativeedge    // 1 clk pulse at falling edge of conditioned
);

    parameter counterwidth = 3; // Counter size, in bits, >= log2(waittime)
    parameter waittime = 3;     // Debounce delay, in clock cycles
    
    reg[counterwidth-1:0] counter = 0;
    reg synchronizer0 = 0;
    reg synchronizer1 = 0;

    always @(posedge clk ) begin
        
        if(conditioned == synchronizer1) begin
            counter <= 0;
            // Reset edge detect
            positiveedge <= 0;
            negativeedge <= 0;
        end
        else begin
            if( counter == waittime) begin
                counter <= 0;
                // Signal about to go through d flip flop. Now is the time to look at 
                if (synchronizer1 == 1 && conditioned == 0)
                    positiveedge <= 1;
                if (synchronizer1 == 0 && conditioned == 1)
                    negativeedge <= 1;
                conditioned <= synchronizer1;
            end
            else 
                counter <= counter+1;
        end

        synchronizer0 <= noisysignal;
        synchronizer1 <= synchronizer0;

    end

endmodule

spimemory.t.v

`include "spimemory.v"

module spimemory_test();

	reg clk, sclk_pin, cs_pin, mosi_pin;
	wire miso_pin;
	wire[3:0] leds;
	wire[4:0] counter;	//leftover for debug


	always #10 clk = !clk;

	parameter write_op = 16'b1010101001110000;
	parameter read_op = 8'b11110000;

	//mosi_pin is input
	//miso_pin is output
	spiMemory dut(.clk(clk), .sclk_pin(sclk_pin), .cs_pin(cs_pin), .miso_pin(miso_pin), .mosi_pin(mosi_pin), .leds(leds));

	initial sclk_pin = 0;
	initial clk = 0;
	initial cs_pin = 1;
	initial mosi_pin = 0;

	initial begin

    $dumpfile("spimemory.vcd"); //Creating .vcd file for timing analysis
    $dumpvars;


    // Write op
    sclk_pin = 1; # 100
    sclk_pin = 0;
	cs_pin = 0;
	mosi_pin = write_op[0]; # 100
	sclk_pin = 1; # 100
    sclk_pin = 0;
	mosi_pin = write_op[1]; # 100
	sclk_pin = 1; # 100
    sclk_pin = 0;
	mosi_pin = write_op[2]; # 100
	sclk_pin = 1; # 100
    sclk_pin = 0;
	mosi_pin = write_op[3]; # 100
	sclk_pin = 1; # 100
    sclk_pin = 0;
	mosi_pin = write_op[4]; # 100
	sclk_pin = 1; # 100
    sclk_pin = 0;
	mosi_pin = write_op[5]; # 100
	sclk_pin = 1; # 100
    sclk_pin = 0;
	mosi_pin = write_op[6]; # 100
	sclk_pin = 1; # 100
    sclk_pin = 0;
	mosi_pin = write_op[7]; # 100
	sclk_pin = 1; # 100
    sclk_pin = 0;
	mosi_pin = write_op[8]; # 100
	sclk_pin = 1; # 100
    sclk_pin = 0;
	mosi_pin = write_op[9]; # 100
	sclk_pin = 1; # 100
    sclk_pin = 0;
	mosi_pin = write_op[10]; # 100
	sclk_pin = 1; # 100
    sclk_pin = 0;
	mosi_pin = write_op[11]; # 100
	sclk_pin = 1; # 100
    sclk_pin = 0;
	mosi_pin = write_op[12]; # 100
	sclk_pin = 1; # 100
    sclk_pin = 0;
	mosi_pin = write_op[13]; # 100
	sclk_pin = 1; # 100
    sclk_pin = 0;
	mosi_pin = write_op[14]; # 100
	sclk_pin = 1; # 100
    sclk_pin = 0;
	mosi_pin = write_op[15]; # 100
	sclk_pin = 1; # 100


	sclk_pin = 0; # 100

    cs_pin = 1; 
    sclk_pin = 1; # 100
    sclk_pin = 0; # 100
    sclk_pin = 1; # 100
    sclk_pin = 0; # 100

    // Read op
    sclk_pin = 1; # 100
    sclk_pin = 0;
	cs_pin = 0;
	mosi_pin = read_op[0]; # 100
	sclk_pin = 1; # 100
    sclk_pin = 0;
	mosi_pin = read_op[1]; # 100
	sclk_pin = 1; # 100
    sclk_pin = 0;
	mosi_pin = read_op[2]; # 100
	sclk_pin = 1; # 100
    sclk_pin = 0;
	mosi_pin = read_op[3]; # 100
	sclk_pin = 1; # 100
    sclk_pin = 0;
	mosi_pin = read_op[4]; # 100
	sclk_pin = 1; # 100
    sclk_pin = 0;
	mosi_pin = read_op[5]; # 100
	sclk_pin = 1; # 100
    sclk_pin = 0;
	mosi_pin = read_op[6]; # 100
	sclk_pin = 1; # 100
    sclk_pin = 0;
	mosi_pin = read_op[7]; # 100
	sclk_pin = 1; # 100

    sclk_pin = 0; # 100
    sclk_pin = 1; # 100
    sclk_pin = 0; # 100
    sclk_pin = 1; # 100
    sclk_pin = 0; # 100
    sclk_pin = 1; # 100
    sclk_pin = 0; # 100

    sclk_pin = 1; # 100
    sclk_pin = 0; # 100
    sclk_pin = 1; # 100
    sclk_pin = 0; # 100
    sclk_pin = 1; # 100
    sclk_pin = 0; # 100
    sclk_pin = 1; # 100
    sclk_pin = 0; # 100
    sclk_pin = 1; # 100
    sclk_pin = 0; # 100
    sclk_pin = 1; # 100
    sclk_pin = 0; # 100
    sclk_pin = 1; # 100
    sclk_pin = 0; # 100
    sclk_pin = 1; # 100
    sclk_pin = 0; # 100
    sclk_pin = 1; # 100
    sclk_pin = 0; # 100
    sclk_pin = 1; # 100
    sclk_pin = 0; # 100


	$finish;

	end

endmodule

spimemory.vcd
$date
	Mon Oct 29 19:49:05 2018
$end
$version
	Icarus Verilog
$end
$timescale
	1s
$end
$scope module spimemory_test $end
$var wire 4 ! leds [3:0] $end
$var wire 1 " miso_pin $end
$var reg 1 # clk $end
$var reg 1 $ cs_pin $end
$var reg 1 % mosi_pin $end
$var reg 1 & sclk_pin $end
$scope module dut $end
$var wire 1 # clk $end
$var wire 1 $ cs_pin $end
$var wire 4 ' leds [3:0] $end
$var wire 1 " miso_pin $end
$var wire 1 % mosi_pin $end
$var wire 1 & sclk_pin $end
$var wire 1 ( sr_we $end
$var wire 1 ) shiftRegOutS $end
$var wire 8 * shiftRegOutP [7:0] $end
$var wire 1 + sclk_pos $end
$var wire 1 , sclk_neg $end
$var wire 1 - sclk_cond $end
$var wire 1 . mosi_pos $end
$var wire 1 / mosi_neg $end
$var wire 1 0 mosi_cond $end
$var wire 1 1 miso_bufe $end
$var wire 1 2 misoPreBufe $end
$var wire 1 3 dm_we $end
$var wire 8 4 dataMemOut [7:0] $end
$var wire 1 5 cs_pos $end
$var wire 1 6 cs_neg $end
$var wire 1 7 cs_cond $end
$var wire 5 8 counter [4:0] $end
$var wire 8 9 addressLatchOut [7:0] $end
$var wire 7 : address [6:0] $end
$var wire 1 ; addr_we $end
$scope module addr_latch $end
$var wire 1 # clk $end
$var wire 1 ; enable $end
$var wire 8 < d [7:0] $end
$var reg 8 = q [7:0] $end
$upscope $end
$scope module data_mem $end
$var wire 7 > address [6:0] $end
$var wire 1 # clk $end
$var wire 1 3 writeEnable $end
$var wire 8 ? dataIn [7:0] $end
$var reg 8 @ dataOut [7:0] $end
$upscope $end
$scope module finite_state_m $end
$var wire 1 A shiftRegOut0 $end
$var wire 1 - sclk $end
$var wire 1 7 cs $end
$var reg 1 3 DM_WE $end
$var reg 1 1 MISO_Buff $end
$var reg 1 ( SR_WE $end
$var reg 1 ; add_WE $end
$var reg 5 B counter [4:0] $end
$var reg 3 C state [2:0] $end
$upscope $end
$scope module ic0 $end
$var wire 1 # clk $end
$var wire 1 % noisysignal $end
$var reg 1 0 conditioned $end
$var reg 3 D counter [2:0] $end
$var reg 1 / negativeedge $end
$var reg 1 . positiveedge $end
$var reg 1 E synchronizer0 $end
$var reg 1 F synchronizer1 $end
$upscope $end
$scope module ic1 $end
$var wire 1 # clk $end
$var wire 1 & noisysignal $end
$var reg 1 - conditioned $end
$var reg 3 G counter [2:0] $end
$var reg 1 , negativeedge $end
$var reg 1 + positiveedge $end
$var reg 1 H synchronizer0 $end
$var reg 1 I synchronizer1 $end
$upscope $end
$scope module ic2 $end
$var wire 1 # clk $end
$var wire 1 $ noisysignal $end
$var reg 1 7 conditioned $end
$var reg 3 J counter [2:0] $end
$var reg 1 6 negativeedge $end
$var reg 1 5 positiveedge $end
$var reg 1 K synchronizer0 $end
$var reg 1 L synchronizer1 $end
$upscope $end
$scope module miso_buff $end
$var wire 1 # clk $end
$var wire 1 , enable $end
$var wire 1 ) d $end
$var reg 1 2 q $end
$upscope $end
$scope module sr $end
$var wire 1 - clk $end
$var wire 8 M parallelDataIn [7:0] $end
$var wire 8 N parallelDataOut [7:0] $end
$var wire 1 ( parallelLoad $end
$var wire 1 + peripheralClkEdge $end
$var wire 1 0 serialDataIn $end
$var wire 1 ) serialDataOut $end
$var reg 8 O shiftregistermem [7:0] $end
$upscope $end
$upscope $end
$upscope $end
$enddefinitions $end
#0
$dumpvars
bx O
bx N
bx M
0L
0K
b0 J
0I
0H
b0 G
0F
0E
b0 D
b101 C
bx B
xA
bx @
bx ?
bx >
bx =
bx <
0;
bx :
bx 9
bx 8
x7
x6
x5
bx 4
03
x2
01
x0
x/
x.
x-
x,
x+
bx *
x)
0(
bz '
1&
0%
1$
0#
z"
bz !
$end
#10
b1 D
1H
b1 G
1K
b1 J
1#
#20
0#
#30
1L
b10 J
1I
b10 G
b10 D
1#
#40
0#
#50
b11 D
b11 G
b11 J
1#
#60
0#
#70
b0 8
b0 B
17
b0 J
1-
b0 G
00
b0 D
1#
#80
0#
#90
0/
0.
0,
0+
06
05
1#
#100
0#
0$
0&
#110
0K
0H
1#
#120
0#
#130
0I
0L
1#
#140
0#
#150
b1 J
b1 G
1#
#160
0#
#170
b10 G
b10 J
1#
#180
0#
#190
b11 J
b11 G
1#
#200
0#
1&
#210
1H
0-
1,
b0 G
07
16
b0 J
1#
#220
0#
#230
06
1I
0,
1#
#240
0#
#250
b1 G
1#
#260
0#
#270
b10 G
1#
#280
0#
#290
b11 G
1#
#300
0#
0&
#310
b1 8
b1 B
0A
bx0 *
bx0 <
bx0 ?
bx0 N
bx0 O
0H
1-
1+
b0 G
1#
#320
0#
#330
0I
0+
1#
#340
0#
#350
b1 G
1#
#360
0#
#370
b10 G
1#
#380
0#
#390
b11 G
1#
#400
0#
1&
#410
1H
0-
1,
b0 G
1#
#420
0#
#430
1I
0,
1#
#440
0#
#450
b1 G
1#
#460
0#
#470
b10 G
1#
#480
0#
#490
b11 G
1#
#500
0#
0&
#510
b10 8
b10 B
bx00 *
bx00 <
bx00 ?
bx00 N
bx00 O
0H
1-
1+
b0 G
1#
#520
0#
#530
0I
0+
1#
#540
0#
#550
b1 G
1#
#560
0#
#570
b10 G
1#
#580
0#
#590
b11 G
1#
#600
0#
1&
#610
1H
0-
1,
b0 G
1#
#620
0#
#630
1I
0,
1#
#640
0#
#650
b1 G
1#
#660
0#
#670
b10 G
1#
#680
0#
#690
b11 G
1#
#700
0#
0&
#710
b11 8
b11 B
bx000 *
bx000 <
bx000 ?
bx000 N
bx000 O
0H
1-
1+
b0 G
1#
#720
0#
#730
0I
0+
1#
#740
0#
#750
b1 G
1#
#760
0#
#770
b10 G
1#
#780
0#
#790
b11 G
1#
#800
0#
1&
#810
1H
0-
1,
b0 G
1#
#820
0#
#830
1I
0,
1#
#840
0#
#850
b1 G
1#
#860
0#
#870
b10 G
1#
#880
0#
#890
b11 G
1#
#900
0#
1%
0&
#910
b100 8
b100 B
bx0000 *
bx0000 <
bx0000 ?
bx0000 N
bx0000 O
0H
1-
1+
b0 G
1E
1#
#920
0#
#930
1F
0I
0+
1#
#940
0#
#950
b1 G
b1 D
1#
#960
0#
#970
b10 D
b10 G
1#
#980
0#
#990
b11 G
b11 D
1#
#1000
0#
1&
#1010
10
1.
b0 D
1H
0-
1,
b0 G
1#
#1020
0#
#1030
1I
0,
0.
1#
#1040
0#
#1050
b1 G
1#
#1060
0#
#1070
b10 G
1#
#1080
0#
#1090
b11 G
1#
#1100
0#
0&
#1110
b101 8
b101 B
1A
bx00001 *
bx00001 <
bx00001 ?
bx00001 N
bx00001 O
0H
1-
1+
b0 G
1#
#1120
0#
#1130
0I
0+
1#
#1140
0#
#1150
b1 G
1#
#1160
0#
#1170
b10 G
1#
#1180
0#
#1190
b11 G
1#
#1200
0#
1&
#1210
1H
0-
1,
b0 G
1#
#1220
0#
#1230
1I
0,
1#
#1240
0#
#1250
b1 G
1#
#1260
0#
#1270
b10 G
1#
#1280
0#
#1290
b11 G
1#
#1300
0#
0&
#1310
b110 8
b110 B
bx000011 *
bx000011 <
bx000011 ?
bx000011 N
bx000011 O
0H
1-
1+
b0 G
1#
#1320
0#
#1330
0I
0+
1#
#1340
0#
#1350
b1 G
1#
#1360
0#
#1370
b10 G
1#
#1380
0#
#1390
b11 G
1#
#1400
0#
1&
#1410
1H
0-
1,
b0 G
1#
#1420
0#
#1430
1I
0,
1#
#1440
0#
#1450
b1 G
1#
#1460
0#
#1470
b10 G
1#
#1480
0#
#1490
b11 G
1#
#1500
0#
0%
0&
#1510
1;
b110 C
b111 8
b111 B
bx0000111 *
bx0000111 <
bx0000111 ?
bx0000111 N
bx0000111 O
0H
1-
1+
b0 G
0E
1#
#1520
0#
#1530
b111 :
b111 >
0F
0I
0+
bx0000111 9
bx0000111 =
1#
#1540
0#
#1550
b1 G
b1 D
1#
#1560
0#
#1570
b10 D
b10 G
1#
#1580
0#
#1590
b11 G
b11 D
1#
#1600
0#
1&
#1610
00
1/
b0 D
1H
0-
1,
b0 G
1#
#1620
0#
#1630
1I
0,
0/
1#
#1640
0#
#1650
b1 G
1#
#1660
0#
#1670
b10 G
1#
#1680
0#
#1690
b11 G
1#
#1700
0#
0&
#1710
0;
b0 C
b1000 8
b1000 B
0)
0A
b1110 *
b1110 <
b1110 ?
b1110 N
b1110 O
0H
1-
1+
b0 G
1#
#1720
0#
#1730
0I
0+
1#
#1740
0#
#1750
b1 G
1#
#1760
0#
#1770
b10 G
1#
#1780
0#
#1790
b11 G
1#
#1800
0#
1&
#1810
1H
0-
1,
b0 G
1#
#1820
0#
#1830
z"
02
1I
0,
1#
#1840
0#
#1850
b1 G
1#
#1860
0#
#1870
b10 G
1#
#1880
0#
#1890
b11 G
1#
#1900
0#
1%
0&
#1910
b11 C
b0 8
b0 B
b11100 *
b11100 <
b11100 ?
b11100 N
b11100 O
0H
1-
1+
b0 G
1E
1#
#1920
0#
#1930
1F
0I
0+
1#
#1940
0#
#1950
b1 G
b1 D
1#
#1960
0#
#1970
b10 D
b10 G
1#
#1980
0#
#1990
b11 G
b11 D
1#
#2000
0#
1&
#2010
10
1.
b0 D
1H
0-
1,
b0 G
1#
#2020
0#
#2030
1I
0,
0.
1#
#2040
0#
#2050
b1 G
1#
#2060
0#
#2070
b10 G
1#
#2080
0#
#2090
b11 G
1#
#2100
0#
0%
0&
#2110
b1 8
b1 B
1A
b111001 *
b111001 <
b111001 ?
b111001 N
b111001 O
0H
1-
1+
b0 G
0E
1#
#2120
0#
#2130
0F
0I
0+
1#
#2140
0#
#2150
b1 G
b1 D
1#
#2160
0#
#2170
b10 D
b10 G
1#
#2180
0#
#2190
b11 G
b11 D
1#
#2200
0#
1&
#2210
00
1/
b0 D
1H
0-
1,
b0 G
1#
#2220
0#
#2230
1I
0,
0/
1#
#2240
0#
#2250
b1 G
1#
#2260
0#
#2270
b10 G
1#
#2280
0#
#2290
b11 G
1#
#2300
0#
1%
0&
#2310
b10 8
b10 B
0A
b1110010 *
b1110010 <
b1110010 ?
b1110010 N
b1110010 O
0H
1-
1+
b0 G
1E
1#
#2320
0#
#2330
1F
0I
0+
1#
#2340
0#
#2350
b1 G
b1 D
1#
#2360
0#
#2370
b10 D
b10 G
1#
#2380
0#
#2390
b11 G
b11 D
1#
#2400
0#
1&
#2410
10
1.
b0 D
1H
0-
1,
b0 G
1#
#2420
0#
#2430
1I
0,
0.
1#
#2440
0#
#2450
b1 G
1#
#2460
0#
#2470
b10 G
1#
#2480
0#
#2490
b11 G
1#
#2500
0#
0%
0&
#2510
b11 8
b11 B
1A
1)
b11100101 *
b11100101 <
b11100101 ?
b11100101 N
b11100101 O
0H
1-
1+
b0 G
0E
1#
#2520
0#
#2530
0F
0I
0+
1#
#2540
0#
#2550
b1 G
b1 D
1#
#2560
0#
#2570
b10 D
b10 G
1#
#2580
0#
#2590
b11 G
b11 D
1#
#2600
0#
1&
#2610
00
1/
b0 D
1H
0-
1,
b0 G
1#
#2620
0#
#2630
z"
12
1I
0,
0/
1#
#2640
0#
#2650
b1 G
1#
#2660
0#
#2670
b10 G
1#
#2680
0#
#2690
b11 G
1#
#2700
0#
1%
0&
#2710
b100 8
b100 B
0A
b11001010 *
b11001010 <
b11001010 ?
b11001010 N
b11001010 O
0H
1-
1+
b0 G
1E
1#
#2720
0#
#2730
1F
0I
0+
1#
#2740
0#
#2750
b1 G
b1 D
1#
#2760
0#
#2770
b10 D
b10 G
1#
#2780
0#
#2790
b11 G
b11 D
1#
#2800
0#
1&
#2810
10
1.
b0 D
1H
0-
1,
b0 G
1#
#2820
0#
#2830
1I
0,
0.
1#
#2840
0#
#2850
b1 G
1#
#2860
0#
#2870
b10 G
1#
#2880
0#
#2890
b11 G
1#
#2900
0#
0%
0&
#2910
b101 8
b101 B
1A
b10010101 *
b10010101 <
b10010101 ?
b10010101 N
b10010101 O
0H
1-
1+
b0 G
0E
1#
#2920
0#
#2930
0F
0I
0+
1#
#2940
0#
#2950
b1 G
b1 D
1#
#2960
0#
#2970
b10 D
b10 G
1#
#2980
0#
#2990
b11 G
b11 D
1#
#3000
0#
1&
#3010
00
1/
b0 D
1H
0-
1,
b0 G
1#
#3020
0#
#3030
1I
0,
0/
1#
#3040
0#
#3050
b1 G
1#
#3060
0#
#3070
b10 G
1#
#3080
0#
#3090
b11 G
1#
#3100
0#
1%
0&
#3110
b110 8
b110 B
0)
0A
b101010 *
b101010 <
b101010 ?
b101010 N
b101010 O
0H
1-
1+
b0 G
1E
1#
#3120
0#
#3130
1F
0I
0+
1#
#3140
0#
#3150
b1 G
b1 D
1#
#3160
0#
#3170
b10 D
b10 G
1#
#3180
0#
#3190
b11 G
b11 D
1#
#3200
0#
1&
#3210
10
1.
b0 D
1H
0-
1,
b0 G
1#
#3220
0#
#3230
z"
02
1I
0,
0.
1#
#3240
0#
#3250
b1 G
1#
#3260
0#
#3270
b10 G
1#
#3280
0#
#3290
b11 G
1#
#3300
0#
0&
#3310
13
b100 C
b111 8
b111 B
1A
b1010101 *
b1010101 <
b1010101 ?
b1010101 N
b1010101 O
0H
1-
1+
b0 G
1#
#3320
0#
#3330
0I
0+
1#
#3340
0#
#3350
b1010101 4
b1010101 @
b1010101 M
b1 G
1#
#3360
0#
#3370
b10 G
1#
#3380
0#
#3390
b11 G
1#
#3400
0#
1&
1$
#3410
1H
0-
1,
b0 G
1K
1#
#3420
0#
#3430
1L
1I
0,
1#
#3440
0#
#3450
b1 G
b1 J
1#
#3460
0#
#3470
b10 J
b10 G
1#
#3480
0#
#3490
b11 G
b11 J
1#
#3500
0#
0&
#3510
03
b101 C
b0 8
b0 B
1)
b10101011 *
b10101011 <
b10101011 ?
b10101011 N
b10101011 O
17
15
b0 J
0H
1-
1+
b0 G
1#
#3520
0#
#3530
0I
0+
05
1#
#3540
0#
#3550
b1 G
1#
#3560
0#
#3570
b10 G
1#
#3580
0#
#3590
b11 G
1#
#3600
0#
1&
#3610
1H
0-
1,
b0 G
1#
#3620
0#
#3630
z"
12
1I
0,
1#
#3640
0#
#3650
b1 G
1#
#3660
0#
#3670
b10 G
1#
#3680
0#
#3690
b11 G
1#
#3700
0#
0&
#3710
b0 8
b0 B
0)
b1010111 *
b1010111 <
b1010111 ?
b1010111 N
b1010111 O
0H
1-
1+
b0 G
1#
#3720
0#
#3730
0I
0+
1#
#3740
0#
#3750
b1 G
1#
#3760
0#
#3770
b10 G
1#
#3780
0#
#3790
b11 G
1#
#3800
0#
1&
#3810
1H
0-
1,
b0 G
1#
#3820
0#
#3830
z"
02
1I
0,
1#
#3840
0#
#3850
b1 G
1#
#3860
0#
#3870
b10 G
1#
#3880
0#
#3890
b11 G
1#
#3900
0#
0%
0$
0&
#3910
b0 8
b0 B
1)
b10101111 *
b10101111 <
b10101111 ?
b10101111 N
b10101111 O
0K
0H
1-
1+
b0 G
0E
1#
#3920
0#
#3930
0F
0I
0+
0L
1#
#3940
0#
#3950
b1 J
b1 G
b1 D
1#
#3960
0#
#3970
b10 D
b10 G
b10 J
1#
#3980
0#
#3990
b11 J
b11 G
b11 D
1#
#4000
0#
1&
#4010
00
1/
b0 D
1H
0-
1,
b0 G
07
16
b0 J
1#
#4020
0#
#4030
z"
12
06
1I
0,
0/
1#
#4040
0#
#4050
b1 G
1#
#4060
0#
#4070
b10 G
1#
#4080
0#
#4090
b11 G
1#
#4100
0#
0&
#4110
b1 8
b1 B
0)
0A
b1011110 *
b1011110 <
b1011110 ?
b1011110 N
b1011110 O
0H
1-
1+
b0 G
1#
#4120
0#
#4130
0I
0+
1#
#4140
0#
#4150
b1 G
1#
#4160
0#
#4170
b10 G
1#
#4180
0#
#4190
b11 G
1#
#4200
0#
1&
#4210
1H
0-
1,
b0 G
1#
#4220
0#
#4230
z"
02
1I
0,
1#
#4240
0#
#4250
b1 G
1#
#4260
0#
#4270
b10 G
1#
#4280
0#
#4290
b11 G
1#
#4300
0#
0&
#4310
b10 8
b10 B
1)
b10111100 *
b10111100 <
b10111100 ?
b10111100 N
b10111100 O
0H
1-
1+
b0 G
1#
#4320
0#
#4330
0I
0+
1#
#4340
0#
#4350
b1 G
1#
#4360
0#
#4370
b10 G
1#
#4380
0#
#4390
b11 G
1#
#4400
0#
1&
#4410
1H
0-
1,
b0 G
1#
#4420
0#
#4430
z"
12
1I
0,
1#
#4440
0#
#4450
b1 G
1#
#4460
0#
#4470
b10 G
1#
#4480
0#
#4490
b11 G
1#
#4500
0#
0&
#4510
b11 8
b11 B
0)
b1111000 *
b1111000 <
b1111000 ?
b1111000 N
b1111000 O
0H
1-
1+
b0 G
1#
#4520
0#
#4530
0I
0+
1#
#4540
0#
#4550
b1 G
1#
#4560
0#
#4570
b10 G
1#
#4580
0#
#4590
b11 G
1#
#4600
0#
1&
#4610
1H
0-
1,
b0 G
1#
